Workbook

Sheet Resumen
B2: UTILIZACION DE LA FLOTA
B3: =Reporte!B3 -> MAGNEX_COL
B5: =+data!A2 -> Fecha del reporte | C5: =data!B2 -> 46202
B6: =data!A5 -> Días | C6: =data!B5 -> 30 | AJ6: =CONCATENATE(PROPER($C$7), " Driven") -> Km Driven
B7: =data!A6 -> Unidad de distancia | C7: =data!B6 -> KM | AJ7: =CONCATENATE(PROPER($C$7)," per day (Avg.)") -> Km per day (Avg.)
B9: =CLEAN(+Reporte!O14) -> (1) DISTANCIA RECORRIDA | K9: =CLEAN(+Reporte!P14) -> (2) DIAS CONDUCIDOS
C11: =UPPER($C$7) -> KM | H11: Vehículos | I11: % | L11: DIAS | Q11: Vehículos | R11: %
B12: Q1 | C12: De | D12: =IF($C$6=90,VLOOKUP($B12,parámetros!$B$4:$D$8,2,FALSE()),0)+IF($C$6=60,VLOOKUP($B12,parámetros!$F$4:$H$8,2,FALSE()),0)+IF(OR($C$6=30,$C$6=31,$C$6=29,$C$6=28),VLOOKUP($B12,parámetros!$J$4:$L$8,2,FALSE()),0)+IF($C$6=7,VLOOKUP($B12,parámetros!$N$4:$P$8,2,FALSE()),0) -> 0 | E12: a | F12: =IF($C$6=90,VLOOKUP($B12,parámetros!$B$4:$D$8,3,FALSE()),0)+IF($C$6=60,VLOOKUP($B12,parámetros!$F$4:$H$8,3,FALSE()),0)+IF(OR($C$6=30,$C$6=31,$C$6=29,$C$6=28),VLOOKUP($B12,parámetros!$J$4:$L$8,3,FALSE()),0)+IF($C$6=7,VLOOKUP($B12,parámetros!$N$4:$P$8,3,FALSE()),0) -> 66.666667 | G12: =IF($C$6=90,VLOOKUP($B12,parámetros!$B$4:$E$8,4,FALSE()),IF($C$6=60,VLOOKUP($B12,parámetros!$F$4:$I$8,4,FALSE()),IF(OR($C$6=30,$C$6=31,$C$6=29,$C$6=28),VLOOKUP($B12,parámetros!$J$4:$M$8,4,FALSE()),IF($C$6=7,VLOOKUP($B12,parámetros!$N$4:$Q$8,4,FALSE()),0)))) -> Menos de 67 | H12: =SUMPRODUCT(SUBTOTAL(3,OFFSET(Reporte!O16:O222,ROW(Reporte!O16:O222)-MIN(ROW(Reporte!O16:O222)),0,1)),(Reporte!O16:O222>=D12)*(Reporte!O16:O222<D13)) -> #VALUE! | I12: =H12/$H$17 -> #VALUE! | K12: Q1 | L12: De | M12: =IF($C$6=90,VLOOKUP($K12,parámetros!$B$12:$D$16,2,FALSE()),0)+IF($C$6=60,VLOOKUP($K12,parámetros!$F$12:$H$16,2,FALSE()),0)+IF(OR($C$6=30,$C$6=31,$C$6=29,$C$6=28),VLOOKUP($K12,parámetros!$J$12:$L$16,2,FALSE()),0)+IF($C$6=7,VLOOKUP($K12,parámetros!$N$12:$P$16,2,FALSE()),0) -> 0 | N12: a | O12: =IF($C$6=90,VLOOKUP($K12,parámetros!$B$12:$D$16,3,FALSE()),0)+IF($C$6=60,VLOOKUP($K12,parámetros!$F$12:$H$16,3,FALSE()),0)+IF(OR($C$6=30,$C$6=31,$C$6=29,$C$6=28),VLOOKUP($K12,parámetros!$J$12:$L$16,3,FALSE()),0)+IF($C$6=7,VLOOKUP($K12,parámetros!$N$12:$P$16,3,FALSE()),0) -> 6 | P12: =IF($C$6=90,VLOOKUP($K12,parámetros!$B$12:$E$16,4,FALSE()),IF($C$6=60,VLOOKUP($K12,parámetros!$F$12:$I$16,4,FALSE()),IF(OR($C$6=30,$C$6=31,$C$6=29,$C$6=28),VLOOKUP($K12,parámetros!$J$12:$M$16,4,FALSE()),IF($C$6=7,VLOOKUP($K12,parámetros!$N$12:$Q$16,4,FALSE()),0)))) -> Menos de 6 | Q12: =SUMPRODUCT(SUBTOTAL(3,OFFSET(Reporte!P16:P222,ROW(Reporte!P16:P222)-MIN(ROW(Reporte!P16:P222)),0,1)),(Reporte!P16:P222>=M12)*(Reporte!P16:P222<M13)) -> #VALUE! | R12: =Q12/$Q$17 -> #VALUE!
B13: Q2 | C13: De | D13: =IF($C$6=90,VLOOKUP($B13,parámetros!$B$4:$D$8,2,FALSE()),0)+IF($C$6=60,VLOOKUP($B13,parámetros!$F$4:$H$8,2,FALSE()),0)+IF(OR($C$6=30,$C$6=31,$C$6=29,$C$6=28),VLOOKUP($B13,parámetros!$J$4:$L$8,2,FALSE()),0)+IF($C$6=7,VLOOKUP($B13,parámetros!$N$4:$P$8,2,FALSE()),0) -> 66.666667 | E13: a | F13: =IF($C$6=90,VLOOKUP($B13,parámetros!$B$4:$D$8,3,FALSE()),0)+IF($C$6=60,VLOOKUP($B13,parámetros!$F$4:$H$8,3,FALSE()),0)+IF(OR($C$6=30,$C$6=31,$C$6=29,$C$6=28),VLOOKUP($B13,parámetros!$J$4:$L$8,3,FALSE()),0)+IF($C$6=7,VLOOKUP($B13,parámetros!$N$4:$P$8,3,FALSE()),0) -> 166.66667 | G13: =IF($C$6=90,VLOOKUP($B13,parámetros!$B$4:$E$8,4,FALSE()),IF($C$6=60,VLOOKUP($B13,parámetros!$F$4:$I$8,4,FALSE()),IF(OR($C$6=30,$C$6=31,$C$6=29,$C$6=28),VLOOKUP($B13,parámetros!$J$4:$M$8,4,FALSE()),IF($C$6=7,VLOOKUP($B13,parámetros!$N$4:$Q$8,4,FALSE()),0)))) -> 67 a 167 | H13: =SUMPRODUCT(SUBTOTAL(3,OFFSET(Reporte!O16:O222,ROW(Reporte!O16:O222)-MIN(ROW(Reporte!O16:O222)),0,1)),(Reporte!O16:O222>=D13)*(Reporte!O16:O222<D14)) -> #VALUE! | I13: =H13/$H$17 -> #VALUE! | K13: Q2 | L13: De | M13: =IF($C$6=90,VLOOKUP($K13,parámetros!$B$12:$D$16,2,FALSE()),0)+IF($C$6=60,VLOOKUP($K13,parámetros!$F$12:$H$16,2,FALSE()),0)+IF(OR($C$6=30,$C$6=31,$C$6=29,$C$6=28),VLOOKUP($K13,parámetros!$J$12:$L$16,2,FALSE()),0)+IF($C$6=7,VLOOKUP($K13,parámetros!$N$12:$P$16,2,FALSE()),0) -> 6 | N13: a | O13: =IF($C$6=90,VLOOKUP($K13,parámetros!$B$12:$D$16,3,FALSE()),0)+IF($C$6=60,VLOOKUP($K13,parámetros!$F$12:$H$16,3,FALSE()),0)+IF(OR($C$6=30,$C$6=31,$C$6=29,$C$6=28),VLOOKUP($K13,parámetros!$J$12:$L$16,3,FALSE()),0)+IF($C$6=7,VLOOKUP($K13,parámetros!$N$12:$P$16,3,FALSE()),0) -> 12 | P13: =IF($C$6=90,VLOOKUP($K13,parámetros!$B$12:$E$16,4,FALSE()),IF($C$6=60,VLOOKUP($K13,parámetros!$F$12:$I$16,4,FALSE()),IF(OR($C$6=30,$C$6=31,$C$6=29,$C$6=28),VLOOKUP($K13,parámetros!$J$12:$M$16,4,FALSE()),IF($C$6=7,VLOOKUP($K13,parámetros!$N$12:$Q$16,4,FALSE()),0)))) -> 6 a 12 | Q13: =SUMPRODUCT(SUBTOTAL(3,OFFSET(Reporte!P16:P222,ROW(Reporte!P16:P222)-MIN(ROW(Reporte!P16:P222)),0,1)),(Reporte!P16:P222>=M13)*(Reporte!P16:P222<M14)) -> #VALUE! | R13: =Q13/$Q$17 -> #VALUE!
B14: Q3 | C14: De | D14: =IF($C$6=90,VLOOKUP($B14,parámetros!$B$4:$D$8,2,FALSE()),0)+IF($C$6=60,VLOOKUP($B14,parámetros!$F$4:$H$8,2,FALSE()),0)+IF(OR($C$6=30,$C$6=31,$C$6=29,$C$6=28),VLOOKUP($B14,parámetros!$J$4:$L$8,2,FALSE()),0)+IF($C$6=7,VLOOKUP($B14,parámetros!$N$4:$P$8,2,FALSE()),0) -> 166.66667 | E14: a | F14: =IF($C$6=90,VLOOKUP($B14,parámetros!$B$4:$D$8,3,FALSE()),0)+IF($C$6=60,VLOOKUP($B14,parámetros!$F$4:$H$8,3,FALSE()),0)+IF(OR($C$6=30,$C$6=31,$C$6=29,$C$6=28),VLOOKUP($B14,parámetros!$J$4:$L$8,3,FALSE()),0)+IF($C$6=7,VLOOKUP($B14,parámetros!$N$4:$P$8,3,FALSE()),0) -> 500 | G14: =IF($C$6=90,VLOOKUP($B14,parámetros!$B$4:$E$8,4,FALSE()),IF($C$6=60,VLOOKUP($B14,parámetros!$F$4:$I$8,4,FALSE()),IF(OR($C$6=30,$C$6=31,$C$6=29,$C$6=28),VLOOKUP($B14,parámetros!$J$4:$M$8,4,FALSE()),IF($C$6=7,VLOOKUP($B14,parámetros!$N$4:$Q$8,4,FALSE()),0)))) -> 167 a 500 | H14: =SUMPRODUCT(SUBTOTAL(3,OFFSET(Reporte!O16:O222,ROW(Reporte!O16:O222)-MIN(ROW(Reporte!O16:O222)),0,1)),(Reporte!O16:O222>=D14)*(Reporte!O16:O222<D15)) -> #VALUE! | I14: =H14/$H$17 -> #VALUE! | K14: Q3 | L14: De | M14: =IF($C$6=90,VLOOKUP($K14,parámetros!$B$12:$D$16,2,FALSE()),0)+IF($C$6=60,VLOOKUP($K14,parámetros!$F$12:$H$16,2,FALSE()),0)+IF(OR($C$6=30,$C$6=31,$C$6=29,$C$6=28),VLOOKUP($K14,parámetros!$J$12:$L$16,2,FALSE()),0)+IF($C$6=7,VLOOKUP($K14,parámetros!$N$12:$P$16,2,FALSE()),0) -> 12 | N14: a | O14: =IF($C$6=90,VLOOKUP($K14,parámetros!$B$12:$D$16,3,FALSE()),0)+IF($C$6=60,VLOOKUP($K14,parámetros!$F$12:$H$16,3,FALSE()),0)+IF(OR($C$6=30,$C$6=31,$C$6=29,$C$6=28),VLOOKUP($K14,parámetros!$J$12:$L$16,3,FALSE()),0)+IF($C$6=7,VLOOKUP($K14,parámetros!$N$12:$P$16,3,FALSE()),0) -> 18 | P14: =IF($C$6=90,VLOOKUP($K14,parámetros!$B$12:$E$16,4,FALSE()),IF($C$6=60,VLOOKUP($K14,parámetros!$F$12:$I$16,4,FALSE()),IF(OR($C$6=30,$C$6=31,$C$6=29,$C$6=28),VLOOKUP($K14,parámetros!$J$12:$M$16,4,FALSE()),IF($C$6=7,VLOOKUP($K14,parámetros!$N$12:$Q$16,4,FALSE()),0)))) -> 12 a 18 | Q14: =SUMPRODUCT(SUBTOTAL(3,OFFSET(Reporte!P16:P222,ROW(Reporte!P16:P222)-MIN(ROW(Reporte!P16:P222)),0,1)),(Reporte!P16:P222>=M14)*(Reporte!P16:P222<M15)) -> #VALUE! | R14: =Q14/$Q$17 -> #VALUE!
B15: Q4 | C15: De | D15: =IF($C$6=90,VLOOKUP($B15,parámetros!$B$4:$D$8,2,FALSE()),0)+IF($C$6=60,VLOOKUP($B15,parámetros!$F$4:$H$8,2,FALSE()),0)+IF(OR($C$6=30,$C$6=31,$C$6=29,$C$6=28),VLOOKUP($B15,parámetros!$J$4:$L$8,2,FALSE()),0)+IF($C$6=7,VLOOKUP($B15,parámetros!$N$4:$P$8,2,FALSE()),0) -> 500 | E15: a | F15: =IF($C$6=90,VLOOKUP($B15,parámetros!$B$4:$D$8,3,FALSE()),0)+IF($C$6=60,VLOOKUP($B15,parámetros!$F$4:$H$8,3,FALSE()),0)+IF(OR($C$6=30,$C$6=31,$C$6=29,$C$6=28),VLOOKUP($B15,parámetros!$J$4:$L$8,3,FALSE()),0)+IF($C$6=7,VLOOKUP($B15,parámetros!$N$4:$P$8,3,FALSE()),0) -> 1000 | G15: =IF($C$6=90,VLOOKUP($B15,parámetros!$B$4:$E$8,4,FALSE()),IF($C$6=60,VLOOKUP($B15,parámetros!$F$4:$I$8,4,FALSE()),IF(OR($C$6=30,$C$6=31,$C$6=29,$C$6=28),VLOOKUP($B15,parámetros!$J$4:$M$8,4,FALSE()),IF($C$6=7,VLOOKUP($B15,parámetros!$N$4:$Q$8,4,FALSE()),0)))) -> 500 a 1,000 | H15: =SUMPRODUCT(SUBTOTAL(3,OFFSET(Reporte!O16:O222,ROW(Reporte!O16:O222)-MIN(ROW(Reporte!O16:O222)),0,1)),(Reporte!O16:O222>=D15)*(Reporte!O16:O222<D16)) -> #VALUE! | I15: =H15/$H$17 -> #VALUE! | K15: Q4 | L15: De | M15: =IF($C$6=90,VLOOKUP($K15,parámetros!$B$12:$D$16,2,FALSE()),0)+IF($C$6=60,VLOOKUP($K15,parámetros!$F$12:$H$16,2,FALSE()),0)+IF(OR($C$6=30,$C$6=31,$C$6=29,$C$6=28),VLOOKUP($K15,parámetros!$J$12:$L$16,2,FALSE()),0)+IF($C$6=7,VLOOKUP($K15,parámetros!$N$12:$P$16,2,FALSE()),0) -> 18 | N15: a | O15: =IF($C$6=90,VLOOKUP($K15,parámetros!$B$12:$D$16,3,FALSE()),0)+IF($C$6=60,VLOOKUP($K15,parámetros!$F$12:$H$16,3,FALSE()),0)+IF(OR($C$6=30,$C$6=31,$C$6=29,$C$6=28),VLOOKUP($K15,parámetros!$J$12:$L$16,3,FALSE()),0)+IF($C$6=7,VLOOKUP($K15,parámetros!$N$12:$P$16,3,FALSE()),0) -> 24 | P15: =IF($C$6=90,VLOOKUP($K15,parámetros!$B$12:$E$16,4,FALSE()),IF($C$6=60,VLOOKUP($K15,parámetros!$F$12:$I$16,4,FALSE()),IF(OR($C$6=30,$C$6=31,$C$6=29,$C$6=28),VLOOKUP($K15,parámetros!$J$12:$M$16,4,FALSE()),IF($C$6=7,VLOOKUP($K15,parámetros!$N$12:$Q$16,4,FALSE()),0)))) -> 18 a 24 | Q15: =SUMPRODUCT(SUBTOTAL(3,OFFSET(Reporte!P16:P222,ROW(Reporte!P16:P222)-MIN(ROW(Reporte!P16:P222)),0,1)),(Reporte!P16:P222>=M15)*(Reporte!P16:P222<M16)) -> #VALUE! | R15: =Q15/$Q$17 -> #VALUE!
B16: Q5 | C16: Más de | D16: =IF($C$6=90,VLOOKUP($B16,parámetros!$B$4:$D$8,2,FALSE()),0)+IF($C$6=60,VLOOKUP($B16,parámetros!$F$4:$H$8,2,FALSE()),0)+IF(OR($C$6=30,$C$6=31,$C$6=29,$C$6=28),VLOOKUP($B16,parámetros!$J$4:$L$8,2,FALSE()),0)+IF($C$6=7,VLOOKUP($B16,parámetros!$N$4:$P$8,2,FALSE()),0) -> 1000 | F16: =IF($C$6=90,VLOOKUP($B16,parámetros!$B$4:$D$8,3,FALSE()),0)+IF($C$6=60,VLOOKUP($B16,parámetros!$F$4:$H$8,3,FALSE()),0)+IF(OR($C$6=30,$C$6=31,$C$6=29,$C$6=28),VLOOKUP($B16,parámetros!$J$4:$L$8,3,FALSE()),0)+IF($C$6=7,VLOOKUP($B16,parámetros!$N$4:$P$8,3,FALSE()),0) -> 0 | G16: =IF($C$6=90,VLOOKUP($B16,parámetros!$B$4:$E$8,4,FALSE()),IF($C$6=60,VLOOKUP($B16,parámetros!$F$4:$I$8,4,FALSE()),IF(OR($C$6=30,$C$6=31,$C$6=29,$C$6=28),VLOOKUP($B16,parámetros!$J$4:$M$8,4,FALSE()),IF($C$6=7,VLOOKUP($B16,parámetros!$N$4:$Q$8,4,FALSE()),0)))) -> Más de 1,000 | H16: =SUMPRODUCT((SUBTOTAL(103,OFFSET(Reporte!O16:O222,ROW(Reporte!O16:O222)-MIN(ROW(Reporte!O16:O222)),0,1)))*(Reporte!O16:O222>=D16)) -> 27 | I16: =H16/$H$17 -> #VALUE! | K16: Q5 | L16: De | M16: =IF($C$6=90,VLOOKUP($K16,parámetros!$B$12:$D$16,2,FALSE()),0)+IF($C$6=60,VLOOKUP($K16,parámetros!$F$12:$H$16,2,FALSE()),0)+IF(OR($C$6=30,$C$6=31,$C$6=29,$C$6=28),VLOOKUP($K16,parámetros!$J$12:$L$16,2,FALSE()),0)+IF($C$6=7,VLOOKUP($K16,parámetros!$N$12:$P$16,2,FALSE()),0) -> 24 | N16: a | O16: =IF($C$6=90,VLOOKUP($K16,parámetros!$B$12:$D$16,3,FALSE()),0)+IF($C$6=60,VLOOKUP($K16,parámetros!$F$12:$H$16,3,FALSE()),0)+IF(OR($C$6=30,$C$6=31,$C$6=29,$C$6=28),VLOOKUP($K16,parámetros!$J$12:$L$16,3,FALSE()),0)+IF($C$6=7,VLOOKUP($K16,parámetros!$N$12:$P$16,3,FALSE()),0) -> 30 | P16: =IF($C$6=90,VLOOKUP($K16,parámetros!$B$12:$E$16,4,FALSE()),IF($C$6=60,VLOOKUP($K16,parámetros!$F$12:$I$16,4,FALSE()),IF(OR($C$6=30,$C$6=31,$C$6=29,$C$6=28),VLOOKUP($K16,parámetros!$J$12:$M$16,4,FALSE()),IF($C$6=7,VLOOKUP($K16,parámetros!$N$12:$Q$16,4,FALSE()),0)))) -> 24 a 30 | Q16: =SUMPRODUCT(SUBTOTAL(103,OFFSET(Reporte!P16:P222,ROW(Reporte!P16:P222)-MIN(ROW(Reporte!P16:P222)),0,1))*(Reporte!P16:P222>=M16)) -> 17 | R16: =Q16/$Q$17 -> #VALUE!
H17: =SUM(H12:H16) -> #VALUE! | Q17: =SUM(Q12:Q16) -> #VALUE!
B18: Uso promedio | C18: =AVERAGE(Reporte!O16:O222) -> 680.07246 | D18: =C7 -> KM | K18: Uso promedio | L18: =AVERAGE(Reporte!P16:P222) -> 8.8067633 | M18: Días
B47: =CLEAN(+Reporte!AC15) -> (3) HORAS DE USO POR DIA | K47: =CLEAN(+Reporte!AD15) -> (4) KM CONDUCIDOS POR DIA
C49: HORAS | H49: Vehículos | I49: % | L49: =UPPER($C$7) -> KM | Q49: Vehículos | R49: %
B50: Q1 | C50: De | D50: 0 | E50: a | F50: 2 | G50: Menos de 2 | H50: =SUMPRODUCT(SUBTOTAL(3,OFFSET(Reporte!AC16:AC222,ROW(Reporte!AC16:AC222)-MIN(ROW(Reporte!AC16:AC222)),0,1)),(Reporte!AC16:AC222>=D50)*(Reporte!AC16:AC222<D51)) -> #VALUE! | I50: =H50/$H$55 -> #VALUE! | K50: Q1 | L50: De | M50: 0 | N50: a | O50: 25 | P50: Menos de 25 | Q50: =SUMPRODUCT(SUBTOTAL(3,OFFSET(Reporte!AD16:AD222,ROW(Reporte!AD16:AD222)-MIN(ROW(Reporte!AD16:AD222)),0,1)),(Reporte!AD16:AD222>=M50)*(Reporte!AD16:AD222<M51)) -> #VALUE! | R50: =Q50/$Q$55 -> #VALUE!
B51: Q2 | C51: De | D51: 2 | E51: a | F51: 4 | G51: 2 a 4 | H51: =SUMPRODUCT(SUBTOTAL(3,OFFSET(Reporte!AC16:AC222,ROW(Reporte!AC16:AC222)-MIN(ROW(Reporte!AC16:AC222)),0,1)),(Reporte!AC16:AC222>=D51)*(Reporte!AC16:AC222<D52)) -> #VALUE! | I51: =H51/$H$55 -> #VALUE! | K51: Q2 | L51: De | M51: 25 | N51: a | O51: 50 | P51: 25 a 50 | Q51: =SUMPRODUCT(SUBTOTAL(3,OFFSET(Reporte!AD16:AD222,ROW(Reporte!AD16:AD222)-MIN(ROW(Reporte!AD16:AD222)),0,1)),(Reporte!AD16:AD222>=M51)*(Reporte!AD16:AD222<M52)) -> #VALUE! | R51: =Q51/$Q$55 -> #VALUE!
B52: Q3 | C52: De | D52: 4 | E52: a | F52: 6 | G52: 4 a 6 | H52: =SUMPRODUCT(SUBTOTAL(3,OFFSET(Reporte!AC16:AC222,ROW(Reporte!AC16:AC222)-MIN(ROW(Reporte!AC16:AC222)),0,1)),(Reporte!AC16:AC222>=D52)*(Reporte!AC16:AC222<D53)) -> #VALUE! | I52: =H52/$H$55 -> #VALUE! | K52: Q3 | L52: De | M52: 50 | N52: a | O52: 100 | P52: 50 a 100 | Q52: =SUMPRODUCT(SUBTOTAL(3,OFFSET(Reporte!AD16:AD222,ROW(Reporte!AD16:AD222)-MIN(ROW(Reporte!AD16:AD222)),0,1)),(Reporte!AD16:AD222>=M52)*(Reporte!AD16:AD222<M53)) -> #VALUE! | R52: =Q52/$Q$55 -> #VALUE!
B53: Q4 | C53: De | D53: 6 | E53: a | F53: 8 | G53: 6 a 8 | H53: =SUMPRODUCT(SUBTOTAL(3,OFFSET(Reporte!AC16:AC222,ROW(Reporte!AC16:AC222)-MIN(ROW(Reporte!AC16:AC222)),0,1)),(Reporte!AC16:AC222>=D53)*(Reporte!AC16:AC222<D54)) -> #VALUE! | I53: =H53/$H$55 -> #VALUE! | K53: Q4 | L53: De | M53: 100 | N53: a | O53: 150 | P53: 100 a 150 | Q53: =SUMPRODUCT(SUBTOTAL(3,OFFSET(Reporte!AD16:AD222,ROW(Reporte!AD16:AD222)-MIN(ROW(Reporte!AD16:AD222)),0,1)),(Reporte!AD16:AD222>=M53)*(Reporte!AD16:AD222<M54)) -> #VALUE! | R53: =Q53/$Q$55 -> #VALUE!
B54: Q5 | C54: Más de | D54: 8 | G54: Más de 8 | H54: =SUMPRODUCT((SUBTOTAL(103,OFFSET(Reporte!AC16:AC222,ROW(Reporte!AC16:AC222)-MIN(ROW(Reporte!AC16:AC222)),0,1)))*(Reporte!AC16:AC222>D54)) -> 46 | I54: =H54/$H$55 -> #VALUE! | K54: Q5 | L54: Más de | M54: 150 | P54: Más de 150 | Q54: =COUNT(_xlfn._xlws.FILTER(Reporte!AD16:AD222,(Reporte!AD16:AD222 > M54)*(SUBTOTAL(103,OFFSET(Reporte!AD16:AD222,ROW(Reporte!AD16:AD222)-MIN(ROW(Reporte!AD16:AD222)),0,1))))) -> 16 | R54: =Q54/$Q$55 -> #VALUE!
H55: =SUM(H50:H54) -> #VALUE! | Q55: =SUM(Q50:Q54) -> #VALUE!
B56: Uso promedio | C56: =AVERAGE(Reporte!AC16:AC222) -> 5.0819391 | D56: Horas/día | K56: Uso promedio | L56: =AVERAGE(Reporte!AD16:AD222) -> 69.719228 | M56: =CONCATENATE(PROPER($C$7),"/día") -> Km/día
H86: TIEMPO PROM. DE CONDUCCION VS. TIEMPO EN RALENTI
I88: Categorías | J88: Horas | K88: %
I89: Tiempo de Conducción | J89: =Reporte!T12 -> 1.3479497 | K89: =J89/$J$91 -> 0.67405568
I90: Tiempo en Ralentí | J90: =Reporte!Y12 -> 0.65181048 | K90: =J90/$J$91 -> 0.32594432
J91: =SUM(J89:J90) -> 1.9997602
C122: =+B9 -> (1) DISTANCIA RECORRIDA | H122: =CONCATENATE("Muestra la apertura de ",LOWER(C7)," conducidos por su flota dentro del período de tiempo especificado.") -> Muestra la apertura de km conducidos por su flota dentro del período de tiempo especificado.
C123: =+K9 -> (2) DIAS CONDUCIDOS | H123: Representa el número de días conducidos por su flota dentro del período de tiempo especificado.
C124: =+B47 -> (3) HORAS DE USO POR DIA | H124: Basado en una jornada laboral promedio de 8 horas, indica el número promedio de horas por día que los vehículos fueron utilizados
C125: =+K47 -> (4) KM CONDUCIDOS POR DIA | H125: =CONCATENATE("Representa el promedio de ",LOWER($C$7)," recorridos por día por los vehículos.") -> Representa el promedio de km recorridos por día por los vehículos.
C126: =+H86 -> TIEMPO PROM. DE CONDUCCION VS. TIEMPO EN RALENTI | H126: Representa el tiempo promedio en que los vehículos fueron utilizados en comparación con el tiempo que estuvieron en ralentí.

Sheet Reporte
B2: UTILIZACION DE LA FLOTA
B3: =+data!B1 -> MAGNEX_COL
B5: =data!A2 -> Fecha del reporte | C5: =data!B2 -> 46202 | AE5: (*) | AF5: Ingrese manualmente el valor deseado para su región en las celdas marcadas en amarillo
B6: =data!A3 -> Desde | C6: =data!B3 -> 46173
B7: =data!A4 -> Hasta | C7: =data!B4 -> 46202 | AE7: JORNADA LABORAL (*) | AH7: Costo promedio del combustible $ (*) | AI7: Consumo promedio de combustible en ralentí por hora
B8: =data!A5 -> Días | C8: =data!B5 -> 30 | AE8: 8 | AF8: HORAS | AH8: 3.5 | AI8: =+IFERROR(VLOOKUP(C9,parámetros!$C$21:$E$22,2,FALSE()),"") -> 1 | AJ8: =+IFERROR(VLOOKUP(C9,parámetros!$C$21:$E$22,3,FALSE()),"") -> Litros | AK8: =+IFERROR(VLOOKUP(E9,parámetros!$C$21:$E$22,2,FALSE()),"")
B9: Unidad de Distancia | C9: =data!B6 -> KM
N10: Odómetro Promedio | O10: PROM. DE DISTANCIA RECORRIDA | P10: PROM. DE DIAS CONDUCIDOS | Q10: TIEMPO PROMEDIO DE CONDUCCION | V10: TIEMPO PROMEDIO EN RALENTI | AA10: Prom. total de tiempo conducido + Ralentí (días) | AC10: UTILIZACION | AJ10: Tabla de referencia rápida
B11: Nota: Tenga en cuenta que sus vehículos solo se mostrarán en el reporte si están asignados a un solo grupo en Geotab. | Q11: Horas | R11: Minutos | S11: Segundos | T11: PROM. TOTAL DE TIEMPO CONDUCIDO (Días) | U11: =+U15 -> % CONDUCIDO | V11: Horas | W11: Minutos | X11: Segundos | Y11: PROM. TOTAL DE TIEMPO EN RALENTI (Días) | Z11: =+Z15 -> % EN RALENTI | AC11: PROM. DE HORAS DE USO POR DIA | AD11: =UPPER(CONCATENATE("PROM.DE ",$C$9," CONDUCIDOS POR DIA")) -> PROM.DE KM CONDUCIDOS POR DIA | AE11: =UPPER(CONCATENATE("VELOCIDAD PROM. (",$C$9," por hora)","")) -> VELOCIDAD PROM. (KM POR HORA) | AF11: PROM. USO DE JORNADA LABORAL(%) | AG11: PROM. DE DIAS CONDUCIDOS (%) | AH11: COSTO TOTAL DE COMBUSTIBLE EN RALENTI | AJ11: 1 Milla | AK11: = | AL11: 1.6 Kilómetros
N12: =SUBTOTAL(1,N$16:N$222) -> 56168.444 | O12: =SUBTOTAL(1,O$16:O$222) -> 680.07246 | P12: =SUBTOTAL(1,P$16:P$222) -> 8.8067633 | Q12: =SUBTOTAL(1,Q$16:Q$222) -> 31.855072 | R12: =SUBTOTAL(1,R$16:R$222) -> 29.285024 | S12: =SUBTOTAL(1,S$16:S$222) -> 27.492754 | T12: =SUBTOTAL(1,T$16:T$222)/24 -> 1.3479497 | U12: =SUBTOTAL(1,U$16:U$222) -> 0.64937327 | V12: =SUBTOTAL(1,V$16:V$222) -> 15.164251 | W12: =SUBTOTAL(1,W$16:W$222) -> 28.309179 | X12: =SUBTOTAL(1,X$16:X$222) -> 26.570048 | Y12: =SUBTOTAL(1,Y$16:Y$222)/24 -> 0.65181048 | Z12: =SUBTOTAL(1,Z$16:Z$222) -> 0.33613397 | AA12: =+T12+Y12 -> 1.9997602 | AC12: =SUBTOTAL(1,AC$16:AC$222) -> 5.0819391 | AD12: =SUBTOTAL(1,AD$16:AD$222) -> 69.719228 | AE12: =SUBTOTAL(1,AE$16:AE$222) -> 20.078848 | AF12: =SUBTOTAL(1,AF$16:AF$222) -> 0.63524239 | AG12: =SUBTOTAL(1,AG$16:AG$222) -> 0.29355878 | AH12: =SUBTOTAL(9,AH$16:AH$222) -> 11333.681 | AJ12: 1 Galón | AK12: = | AL12: 3.78541 Litros
AJ13: 1 USD | AK13: = | AL13: 1.42 CAD
B14: Grupo1 | C14: Grupo2 | D14: Grupo3 | E14: Grupo4 | F14: Grupo5 | G14: Grupo6 | H14: Grupo7 | I14: Grupo8 | J14: Vehículo | K14: Conductor | L14: GPS | M14: Cámara | N14: Odómetro | O14: (1) DISTANCIA RECORRIDA | P14: (2) DIAS CONDUCIDOS | Q14: TIEMPO CONDUCIDO | V14: TIEMPO EN RALENTI | AA14: Tiempo total conducido + Ralentí (horas) | AC14: UTILIZACION | AJ14: 1 USD | AK14: = | AL14: 0.95 EUR
Q15: Horas | R15: Minutos | S15: Segundos | T15: TIEMPO NETO CONDUCIDO (Horas) | U15: % CONDUCIDO | V15: Horas | W15: Minutos | X15: Segundos | Y15: TIEMPO NETO EN RALENTI (Horas) | Z15: % EN RALENTI | AC15: (3) HORAS DE USO POR DIA | AD15: =UPPER(CONCATENATE("(4) ",$C$9," CONDUCIDOS POR DIA")) -> (4) KM CONDUCIDOS POR DIA | AE15: =+AE11 -> VELOCIDAD PROM. (KM POR HORA) | AF15: USO DE JORNADA LABORAL (%) | AG15: DIAS CONDUCIDOS (%) | AH15: COSTO DE COMBUSTIBLE EN RALENTI
B16: Magnex | C16: Zona Generación | D16: ECP 1107 Rubiales Serv. Integrales | J16: QLO286 | L16: ✔️ | M16: =data!J8 -> 30 | N16: 30820 | O16: 6044 | P16: 30 | Q16: 324 | R16: 19 | S16: 25 | T16: =+((Q16)+(R16/60)+(S16/3600)) -> 324.32361 | U16: =IFERROR(T16/$AA16,0) -> 0.82928245 | V16: 66 | W16: 45 | X16: 57 | Y16: =+((V16)+(W16/60)+(X16/3600)) -> 66.765833 | Z16: =+IFERROR(Y16/$AA16,0) -> 0.17071755 | AA16: =+Y16+T16 -> 391.08944 | AC16: =+IFERROR((AA16/P16),0) -> 13.036315 | AD16: =+IFERROR($O16/$P16,0) -> 201.46667 | AE16: =+IFERROR(O16/T16,0) -> 18.635708 | AF16: =+IFERROR(AA16/(P16*$AE$8),0) -> 1.6295394 | AG16: =+P16/$C$8 -> 1 | AH16: =+Y16*($AI$8*$AH$8) -> 233.68042
B17: Magnex | C17: Zona Centro | D17: GMA CENTRO | J17: NPY686 | L17: ✔️ | M17: =data!J8 -> 30 | N17: 24050 | O17: 1208 | P17: 22 | Q17: 42 | R17: 3 | S17: 4 | T17: =+((Q17)+(R17/60)+(S17/3600)) -> 42.051111 | U17: =IFERROR(T17/$AA17,0) -> 0.87050327 | V17: 6 | W17: 15 | X17: 20 | Y17: =+((V17)+(W17/60)+(X17/3600)) -> 6.2555556 | Z17: =+IFERROR(Y17/$AA17,0) -> 0.12949673 | AA17: =+Y17+T17 -> 48.306667 | AC17: =+IFERROR((AA17/P17),0) -> 2.1957576 | AD17: =+IFERROR($O17/$P17,0) -> 54.909091 | AE17: =+IFERROR(O17/T17,0) -> 28.726946 | AF17: =+IFERROR(AA17/(P17*$AE$8),0) -> 0.2744697 | AG17: =+P17/$C$8 -> 0.73333333 | AH17: =+Y17*($AI$8*$AH$8) -> 21.894444
B18: Magnex | C18: Zona Energy | D18: ENEL 6053 Zona III OPEX SOT SOC-GA | J18: PMV840 | L18: ✔️ | M18: =data!J8 -> 30 | N18: 7510 | O18: 483 | P18: 20 | Q18: 37 | R18: 13 | S18: 50 | T18: =+((Q18)+(R18/60)+(S18/3600)) -> 37.230556 | U18: =IFERROR(T18/$AA18,0) -> 0.69840029 | V18: 16 | W18: 4 | X18: 40 | Y18: =+((V18)+(W18/60)+(X18/3600)) -> 16.077778 | Z18: =+IFERROR(Y18/$AA18,0) -> 0.30159971 | AA18: =+Y18+T18 -> 53.308333 | AC18: =+IFERROR((AA18/P18),0) -> 2.6654167 | AD18: =+IFERROR($O18/$P18,0) -> 24.15 | AE18: =+IFERROR(O18/T18,0) -> 12.973215 | AF18: =+IFERROR(AA18/(P18*$AE$8),0) -> 0.33317708 | AG18: =+P18/$C$8 -> 0.66666667 | AH18: =+Y18*($AI$8*$AH$8) -> 56.272222
B19: Magnex | C19: Zona Energy | D19: ENEL 6053 Zona III OPEX SOT SOC-GA | J19: NPY798 | L19: ✔️ | M19: =data!J8 -> 30 | N19: 10809 | O19: 860 | P19: 26 | Q19: 66 | R19: 33 | S19: 51 | T19: =+((Q19)+(R19/60)+(S19/3600)) -> 66.564167 | U19: =IFERROR(T19/$AA19,0) -> 0.71892391 | V19: 26 | W19: 1 | X19: 28 | Y19: =+((V19)+(W19/60)+(X19/3600)) -> 26.024444 | Z19: =+IFERROR(Y19/$AA19,0) -> 0.28107609 | AA19: =+Y19+T19 -> 92.588611 | AC19: =+IFERROR((AA19/P19),0) -> 3.5611004 | AD19: =+IFERROR($O19/$P19,0) -> 33.076923 | AE19: =+IFERROR(O19/T19,0) -> 12.919864 | AF19: =+IFERROR(AA19/(P19*$AE$8),0) -> 0.44513755 | AG19: =+P19/$C$8 -> 0.86666667 | AH19: =+Y19*($AI$8*$AH$8) -> 91.085556
B20: Magnex | C20: Zona Energy | D20: ENEL 6054 Zona V OPEX SOT SOC-GA | J20: GSO698 | L20: ✔️ | M20: =data!J8 -> 30 | N20: 138492 | O20: 3187 | P20: 24 | Q20: 131 | R20: 38 | S20: 31 | T20: =+((Q20)+(R20/60)+(S20/3600)) -> 131.64194 | U20: =IFERROR(T20/$AA20,0) -> 0.76999103 | V20: 39 | W20: 19 | X20: 25 | Y20: =+((V20)+(W20/60)+(X20/3600)) -> 39.323611 | Z20: =+IFERROR(Y20/$AA20,0) -> 0.23000897 | AA20: =+Y20+T20 -> 170.96556 | AC20: =+IFERROR((AA20/P20),0) -> 7.1235648 | AD20: =+IFERROR($O20/$P20,0) -> 132.79167 | AE20: =+IFERROR(O20/T20,0) -> 24.209609 | AF20: =+IFERROR(AA20/(P20*$AE$8),0) -> 0.8904456 | AG20: =+P20/$C$8 -> 0.8 | AH20: =+Y20*($AI$8*$AH$8) -> 137.63264
B21: Magnex | C21: Zona Energy | D21: ENEL 6054 Zona V OPEX SOT SOC-GA | J21: NPY979 | L21: ✔️ | M21: =data!J8 -> 30 | N21: 20833 | O21: 1701 | P21: 20 | Q21: 72 | R21: 58 | S21: 59 | T21: =+((Q21)+(R21/60)+(S21/3600)) -> 72.983056 | U21: =IFERROR(T21/$AA21,0) -> 0.72172915 | V21: 28 | W21: 8 | X21: 22 | Y21: =+((V21)+(W21/60)+(X21/3600)) -> 28.139444 | Z21: =+IFERROR(Y21/$AA21,0) -> 0.27827085 | AA21: =+Y21+T21 -> 101.1225 | AC21: =+IFERROR((AA21/P21),0) -> 5.056125 | AD21: =+IFERROR($O21/$P21,0) -> 85.05 | AE21: =+IFERROR(O21/T21,0) -> 23.30678 | AF21: =+IFERROR(AA21/(P21*$AE$8),0) -> 0.63201562 | AG21: =+P21/$C$8 -> 0.66666667 | AH21: =+Y21*($AI$8*$AH$8) -> 98.488056
B22: Magnex | C22: Zona Energy | D22: ENEL 6054 Zona V OPEX SOT SOC-GA | J22: NPY794 | L22: ✔️ | M22: =data!J8 -> 30 | N22: 21171 | O22: 1042 | P22: 22 | Q22: 57 | R22: 40 | S22: 3 | T22: =+((Q22)+(R22/60)+(S22/3600)) -> 57.6675 | U22: =IFERROR(T22/$AA22,0) -> 0.79426652 | V22: 14 | W22: 56 | X22: 14 | Y22: =+((V22)+(W22/60)+(X22/3600)) -> 14.937222 | Z22: =+IFERROR(Y22/$AA22,0) -> 0.20573348 | AA22: =+Y22+T22 -> 72.604722 | AC22: =+IFERROR((AA22/P22),0) -> 3.3002146 | AD22: =+IFERROR($O22/$P22,0) -> 47.363636 | AE22: =+IFERROR(O22/T22,0) -> 18.069103 | AF22: =+IFERROR(AA22/(P22*$AE$8),0) -> 0.41252683 | AG22: =+P22/$C$8 -> 0.73333333 | AH22: =+Y22*($AI$8*$AH$8) -> 52.280278
B23: Magnex | C23: Zona Energy | D23: ENEL 6054 Zona V OPEX SOT SOC-GA | J23: NPY609 | L23: ✔️ | M23: =data!J8 -> 30 | N23: 18011 | O23: 1337 | P23: 22 | Q23: 68 | R23: 47 | S23: 36 | T23: =+((Q23)+(R23/60)+(S23/3600)) -> 68.793333 | U23: =IFERROR(T23/$AA23,0) -> 0.67766668 | V23: 32 | W23: 43 | X23: 18 | Y23: =+((V23)+(W23/60)+(X23/3600)) -> 32.721667 | Z23: =+IFERROR(Y23/$AA23,0) -> 0.32233332 | AA23: =+Y23+T23 -> 101.515 | AC23: =+IFERROR((AA23/P23),0) -> 4.6143182 | AD23: =+IFERROR($O23/$P23,0) -> 60.772727 | AE23: =+IFERROR(O23/T23,0) -> 19.435023 | AF23: =+IFERROR(AA23/(P23*$AE$8),0) -> 0.57678977 | AG23: =+P23/$C$8 -> 0.73333333 | AH23: =+Y23*($AI$8*$AH$8) -> 114.52583
B24: Magnex | C24: Zona Energy | D24: ENEL 6054 Zona V OPEX SOT SOC-GA | J24: NPY995 | L24: ✔️ | M24: =data!J8 -> 30 | N24: 18436 | O24: 1167 | P24: 21 | Q24: 56 | R24: 30 | S24: 46 | T24: =+((Q24)+(R24/60)+(S24/3600)) -> 56.512778 | U24: =IFERROR(T24/$AA24,0) -> 0.70863405 | V24: 23 | W24: 14 | X24: 10 | Y24: =+((V24)+(W24/60)+(X24/3600)) -> 23.236111 | Z24: =+IFERROR(Y24/$AA24,0) -> 0.29136595 | AA24: =+Y24+T24 -> 79.748889 | AC24: =+IFERROR((AA24/P24),0) -> 3.7975661 | AD24: =+IFERROR($O24/$P24,0) -> 55.571429 | AE24: =+IFERROR(O24/T24,0) -> 20.650197 | AF24: =+IFERROR(AA24/(P24*$AE$8),0) -> 0.47469577 | AG24: =+P24/$C$8 -> 0.7 | AH24: =+Y24*($AI$8*$AH$8) -> 81.326389
B25: Magnex | C25: Zona Energy | D25: ENEL 6054 Zona V OPEX SOT SOC-GA | J25: JSL414 | L25: ✔️ | M25: =data!J8 -> 30 | N25: 168484 | O25: 338 | P25: 9 | Q25: 14 | R25: 33 | S25: 52 | T25: =+((Q25)+(R25/60)+(S25/3600)) -> 14.564444 | U25: =IFERROR(T25/$AA25,0) -> 0.56339723 | V25: 11 | W25: 17 | X25: 12 | Y25: =+((V25)+(W25/60)+(X25/3600)) -> 11.286667 | Z25: =+IFERROR(Y25/$AA25,0) -> 0.43660277 | AA25: =+Y25+T25 -> 25.851111 | AC25: =+IFERROR((AA25/P25),0) -> 2.8723457 | AD25: =+IFERROR($O25/$P25,0) -> 37.555556 | AE25: =+IFERROR(O25/T25,0) -> 23.207202 | AF25: =+IFERROR(AA25/(P25*$AE$8),0) -> 0.35904321 | AG25: =+P25/$C$8 -> 0.3 | AH25: =+Y25*($AI$8*$AH$8) -> 39.503333
B26: Magnex | C26: Zona Energy | D26: ENEL 6054 Zona V OPEX SOT SOC-GA | J26: GSN681 | L26: ✔️ | M26: =data!J8 -> 30 | N26: 163678 | O26: 1858 | P26: 20 | Q26: 75 | R26: 50 | S26: 34 | T26: =+((Q26)+(R26/60)+(S26/3600)) -> 75.842778 | U26: =IFERROR(T26/$AA26,0) -> 0.7637507 | V26: 23 | W26: 27 | X26: 37 | Y26: =+((V26)+(W26/60)+(X26/3600)) -> 23.460278 | Z26: =+IFERROR(Y26/$AA26,0) -> 0.2362493 | AA26: =+Y26+T26 -> 99.303056 | AC26: =+IFERROR((AA26/P26),0) -> 4.9651528 | AD26: =+IFERROR($O26/$P26,0) -> 92.9 | AE26: =+IFERROR(O26/T26,0) -> 24.498048 | AF26: =+IFERROR(AA26/(P26*$AE$8),0) -> 0.6206441 | AG26: =+P26/$C$8 -> 0.66666667 | AH26: =+Y26*($AI$8*$AH$8) -> 82.110972
B27: Magnex | C27: Zona Energy | D27: ENEL 6054 Zona V OPEX SOT SOC-GA | J27: NPY976 | L27: ✔️ | M27: =data!J8 -> 30 | N27: 21065 | O27: 653 | P27: 19 | Q27: 34 | R27: 1 | S27: 42 | T27: =+((Q27)+(R27/60)+(S27/3600)) -> 34.028333 | U27: =IFERROR(T27/$AA27,0) -> 0.74717754 | V27: 11 | W27: 30 | X27: 51 | Y27: =+((V27)+(W27/60)+(X27/3600)) -> 11.514167 | Z27: =+IFERROR(Y27/$AA27,0) -> 0.25282246 | AA27: =+Y27+T27 -> 45.5425 | AC27: =+IFERROR((AA27/P27),0) -> 2.3969737 | AD27: =+IFERROR($O27/$P27,0) -> 34.368421 | AE27: =+IFERROR(O27/T27,0) -> 19.189891 | AF27: =+IFERROR(AA27/(P27*$AE$8),0) -> 0.29962171 | AG27: =+P27/$C$8 -> 0.63333333 | AH27: =+Y27*($AI$8*$AH$8) -> 40.299583
B28: Magnex | C28: Zona Energy | D28: ENEL 6054 Zona V OPEX SOT SOC-GA | J28: NPY986 | L28: ✔️ | M28: =data!J8 -> 30 | N28: 15024 | O28: 712 | P28: 18 | Q28: 34 | R28: 11 | S28: 37 | T28: =+((Q28)+(R28/60)+(S28/3600)) -> 34.193611 | U28: =IFERROR(T28/$AA28,0) -> 0.68728958 | V28: 15 | W28: 33 | X28: 28 | Y28: =+((V28)+(W28/60)+(X28/3600)) -> 15.557778 | Z28: =+IFERROR(Y28/$AA28,0) -> 0.31271042 | AA28: =+Y28+T28 -> 49.751389 | AC28: =+IFERROR((AA28/P28),0) -> 2.763966 | AD28: =+IFERROR($O28/$P28,0) -> 39.555556 | AE28: =+IFERROR(O28/T28,0) -> 20.822603 | AF28: =+IFERROR(AA28/(P28*$AE$8),0) -> 0.34549576 | AG28: =+P28/$C$8 -> 0.6 | AH28: =+Y28*($AI$8*$AH$8) -> 54.452222
B29: Magnex | C29: Zona Energy | D29: ENEL 6054 Zona V OPEX SOT SOC-GA | J29: NPY990 | L29: ✔️ | M29: =data!J8 -> 30 | N29: 19495 | O29: 1399 | P29: 21 | Q29: 62 | R29: 49 | S29: 30 | T29: =+((Q29)+(R29/60)+(S29/3600)) -> 62.825 | U29: =IFERROR(T29/$AA29,0) -> 0.89299957 | V29: 7 | W29: 31 | X29: 40 | Y29: =+((V29)+(W29/60)+(X29/3600)) -> 7.5277778 | Z29: =+IFERROR(Y29/$AA29,0) -> 0.10700043 | AA29: =+Y29+T29 -> 70.352778 | AC29: =+IFERROR((AA29/P29),0) -> 3.3501323 | AD29: =+IFERROR($O29/$P29,0) -> 66.619048 | AE29: =+IFERROR(O29/T29,0) -> 22.268205 | AF29: =+IFERROR(AA29/(P29*$AE$8),0) -> 0.41876653 | AG29: =+P29/$C$8 -> 0.7 | AH29: =+Y29*($AI$8*$AH$8) -> 26.347222
B30: Magnex | C30: Zona Energy | D30: ENEL 6054 Zona V OPEX SOT SOC-GA | J30: LJQ948 | L30: ✔️ | M30: =data!J8 -> 30 | N30: 203210 | O30: 493 | P30: 16 | Q30: 25 | R30: 35 | S30: 39 | T30: =+((Q30)+(R30/60)+(S30/3600)) -> 25.594167 | U30: =IFERROR(T30/$AA30,0) -> 0.39540902 | V30: 39 | W30: 8 | X30: 3 | Y30: =+((V30)+(W30/60)+(X30/3600)) -> 39.134167 | Z30: =+IFERROR(Y30/$AA30,0) -> 0.60459098 | AA30: =+Y30+T30 -> 64.728333 | AC30: =+IFERROR((AA30/P30),0) -> 4.0455208 | AD30: =+IFERROR($O30/$P30,0) -> 30.8125 | AE30: =+IFERROR(O30/T30,0) -> 19.262202 | AF30: =+IFERROR(AA30/(P30*$AE$8),0) -> 0.5056901 | AG30: =+P30/$C$8 -> 0.53333333 | AH30: =+Y30*($AI$8*$AH$8) -> 136.96958
B31: Magnex | C31: Zona Energy | D31: ENEL 6054 Zona V OPEX SOT SOC-GA | J31: NFX476 | L31: ✔️ | M31: =data!J8 -> 30 | N31: 96440 | O31: 852 | P31: 15 | Q31: 38 | R31: 24 | S31: 2 | T31: =+((Q31)+(R31/60)+(S31/3600)) -> 38.400556 | U31: =IFERROR(T31/$AA31,0) -> 0.74077527 | V31: 13 | W31: 26 | X31: 16 | Y31: =+((V31)+(W31/60)+(X31/3600)) -> 13.437778 | Z31: =+IFERROR(Y31/$AA31,0) -> 0.25922473 | AA31: =+Y31+T31 -> 51.838333 | AC31: =+IFERROR((AA31/P31),0) -> 3.4558889 | AD31: =+IFERROR($O31/$P31,0) -> 56.8 | AE31: =+IFERROR(O31/T31,0) -> 22.187179 | AF31: =+IFERROR(AA31/(P31*$AE$8),0) -> 0.43198611 | AG31: =+P31/$C$8 -> 0.5 | AH31: =+Y31*($AI$8*$AH$8) -> 47.032222
B32: Magnex | C32: Zona Energy | D32: ENEL 6054 Zona V OPEX SOT SOC-GA | J32: NPY987 | L32: ✔️ | M32: =data!J8 -> 30 | N32: 13527 | O32: 661 | P32: 13 | Q32: 31 | R32: 26 | S32: 59 | T32: =+((Q32)+(R32/60)+(S32/3600)) -> 31.449722 | U32: =IFERROR(T32/$AA32,0) -> 0.55483463 | V32: 25 | W32: 14 | X32: 0 | Y32: =+((V32)+(W32/60)+(X32/3600)) -> 25.233333 | Z32: =+IFERROR(Y32/$AA32,0) -> 0.44516537 | AA32: =+Y32+T32 -> 56.683056 | AC32: =+IFERROR((AA32/P32),0) -> 4.360235 | AD32: =+IFERROR($O32/$P32,0) -> 50.846154 | AE32: =+IFERROR(O32/T32,0) -> 21.017674 | AF32: =+IFERROR(AA32/(P32*$AE$8),0) -> 0.54502938 | AG32: =+P32/$C$8 -> 0.43333333 | AH32: =+Y32*($AI$8*$AH$8) -> 88.316667
B33: Magnex | C33: Zona Energy | D33: ENEL 6054 Zona V OPEX SOT SOC-GA | J33: NPY628 | L33: ✔️ | M33: =data!J8 -> 30 | N33: 13083 | O33: 1046 | P33: 18 | Q33: 52 | R33: 27 | S33: 51 | T33: =+((Q33)+(R33/60)+(S33/3600)) -> 52.464167 | U33: =IFERROR(T33/$AA33,0) -> 0.45248317 | V33: 63 | W33: 28 | X33: 59 | Y33: =+((V33)+(W33/60)+(X33/3600)) -> 63.483056 | Z33: =+IFERROR(Y33/$AA33,0) -> 0.54751683 | AA33: =+Y33+T33 -> 115.94722 | AC33: =+IFERROR((AA33/P33),0) -> 6.4415123 | AD33: =+IFERROR($O33/$P33,0) -> 58.111111 | AE33: =+IFERROR(O33/T33,0) -> 19.937418 | AF33: =+IFERROR(AA33/(P33*$AE$8),0) -> 0.80518904 | AG33: =+P33/$C$8 -> 0.6 | AH33: =+Y33*($AI$8*$AH$8) -> 222.19069
B34: Magnex | C34: Zona Energy | D34: ENEL 6054 Zona V OPEX SOT SOC-GA | J34: NPY978 | L34: ✔️ | M34: =data!J8 -> 30 | N34: 17791 | O34: 858 | P34: 17 | Q34: 40 | R34: 39 | S34: 2 | T34: =+((Q34)+(R34/60)+(S34/3600)) -> 40.650556 | U34: =IFERROR(T34/$AA34,0) -> 0.67197789 | V34: 19 | W34: 50 | X34: 36 | Y34: =+((V34)+(W34/60)+(X34/3600)) -> 19.843333 | Z34: =+IFERROR(Y34/$AA34,0) -> 0.32802211 | AA34: =+Y34+T34 -> 60.493889 | AC34: =+IFERROR((AA34/P34),0) -> 3.5584641 | AD34: =+IFERROR($O34/$P34,0) -> 50.470588 | AE34: =+IFERROR(O34/T34,0) -> 21.106723 | AF34: =+IFERROR(AA34/(P34*$AE$8),0) -> 0.44480801 | AG34: =+P34/$C$8 -> 0.56666667 | AH34: =+Y34*($AI$8*$AH$8) -> 69.451667
B35: Magnex | C35: Zona Energy | D35: ENEL 6054 Zona V OPEX SOT SOC-GA | J35: JSL356 | L35: ✔️ | M35: =data!J8 -> 30 | N35: 178134 | O35: 565 | P35: 12 | Q35: 41 | R35: 3 | S35: 45 | T35: =+((Q35)+(R35/60)+(S35/3600)) -> 41.0625 | U35: =IFERROR(T35/$AA35,0) -> 0.49056535 | V35: 42 | W35: 38 | X35: 31 | Y35: =+((V35)+(W35/60)+(X35/3600)) -> 42.641944 | Z35: =+IFERROR(Y35/$AA35,0) -> 0.50943465 | AA35: =+Y35+T35 -> 83.704444 | AC35: =+IFERROR((AA35/P35),0) -> 6.9753704 | AD35: =+IFERROR($O35/$P35,0) -> 47.083333 | AE35: =+IFERROR(O35/T35,0) -> 13.759513 | AF35: =+IFERROR(AA35/(P35*$AE$8),0) -> 0.8719213 | AG35: =+P35/$C$8 -> 0.4 | AH35: =+Y35*($AI$8*$AH$8) -> 149.24681
B36: Magnex | C36: Zona Energy | D36: ENEL 6054 Zona V OPEX SOT SOC-GA | J36: NPZ118 | L36: ✔️ | M36: =data!J8 -> 30 | N36: 21418 | O36: 373 | P36: 13 | Q36: 17 | R36: 48 | S36: 43 | T36: =+((Q36)+(R36/60)+(S36/3600)) -> 17.811944 | U36: =IFERROR(T36/$AA36,0) -> 0.67945621 | V36: 8 | W36: 24 | X36: 11 | Y36: =+((V36)+(W36/60)+(X36/3600)) -> 8.4030556 | Z36: =+IFERROR(Y36/$AA36,0) -> 0.32054379 | AA36: =+Y36+T36 -> 26.215 | AC36: =+IFERROR((AA36/P36),0) -> 2.0165385 | AD36: =+IFERROR($O36/$P36,0) -> 28.692308 | AE36: =+IFERROR(O36/T36,0) -> 20.941004 | AF36: =+IFERROR(AA36/(P36*$AE$8),0) -> 0.25206731 | AG36: =+P36/$C$8 -> 0.43333333 | AH36: =+Y36*($AI$8*$AH$8) -> 29.410694
B37: Magnex | C37: Zona Energy | D37: ENEL 6054 Zona V OPEX SOT SOC-GA | J37: GEU353 | L37: ✔️ | M37: =data!J8 -> 30 | N37: 117720 | O37: 512 | P37: 14 | Q37: 25 | R37: 11 | S37: 37 | T37: =+((Q37)+(R37/60)+(S37/3600)) -> 25.193611 | U37: =IFERROR(T37/$AA37,0) -> 0.70589563 | V37: 10 | W37: 29 | X37: 48 | Y37: =+((V37)+(W37/60)+(X37/3600)) -> 10.496667 | Z37: =+IFERROR(Y37/$AA37,0) -> 0.29410437 | AA37: =+Y37+T37 -> 35.690278 | AC37: =+IFERROR((AA37/P37),0) -> 2.5493056 | AD37: =+IFERROR($O37/$P37,0) -> 36.571429 | AE37: =+IFERROR(O37/T37,0) -> 20.322613 | AF37: =+IFERROR(AA37/(P37*$AE$8),0) -> 0.31866319 | AG37: =+P37/$C$8 -> 0.46666667 | AH37: =+Y37*($AI$8*$AH$8) -> 36.738333
B38: Magnex | C38: Zona Energy | D38: ENEL 6054 Zona V OPEX SOT SOC-GA | J38: NPY988 | L38: ✔️ | M38: =data!J8 -> 30 | N38: 17532 | O38: 623 | P38: 14 | Q38: 30 | R38: 6 | S38: 28 | T38: =+((Q38)+(R38/60)+(S38/3600)) -> 30.107778 | U38: =IFERROR(T38/$AA38,0) -> 0.84871739 | V38: 5 | W38: 22 | X38: 0 | Y38: =+((V38)+(W38/60)+(X38/3600)) -> 5.3666667 | Z38: =+IFERROR(Y38/$AA38,0) -> 0.15128261 | AA38: =+Y38+T38 -> 35.474444 | AC38: =+IFERROR((AA38/P38),0) -> 2.5338889 | AD38: =+IFERROR($O38/$P38,0) -> 44.5 | AE38: =+IFERROR(O38/T38,0) -> 20.692328 | AF38: =+IFERROR(AA38/(P38*$AE$8),0) -> 0.31673611 | AG38: =+P38/$C$8 -> 0.46666667 | AH38: =+Y38*($AI$8*$AH$8) -> 18.783333
B39: Magnex | C39: Zona Energy | D39: ENEL 6054 Zona V OPEX SOT SOC-GA | J39: PMV835 | L39: ✔️ | M39: =data!J8 -> 30 | N39: 13136 | O39: 431 | P39: 14 | Q39: 20 | R39: 31 | S39: 47 | T39: =+((Q39)+(R39/60)+(S39/3600)) -> 20.529722 | U39: =IFERROR(T39/$AA39,0) -> 0.76790483 | V39: 6 | W39: 12 | X39: 18 | Y39: =+((V39)+(W39/60)+(X39/3600)) -> 6.205 | Z39: =+IFERROR(Y39/$AA39,0) -> 0.23209517 | AA39: =+Y39+T39 -> 26.734722 | AC39: =+IFERROR((AA39/P39),0) -> 1.909623 | AD39: =+IFERROR($O39/$P39,0) -> 30.785714 | AE39: =+IFERROR(O39/T39,0) -> 20.993952 | AF39: =+IFERROR(AA39/(P39*$AE$8),0) -> 0.23870288 | AG39: =+P39/$C$8 -> 0.46666667 | AH39: =+Y39*($AI$8*$AH$8) -> 21.7175
B40: Magnex | C40: Zona Energy | D40: ENEL 6054 Zona V OPEX SOT SOC-GA | J40: NPY973 | L40: ✔️ | M40: =data!J8 -> 30 | N40: 16314 | O40: 426 | P40: 10 | Q40: 26 | R40: 31 | S40: 6 | T40: =+((Q40)+(R40/60)+(S40/3600)) -> 26.518333 | U40: =IFERROR(T40/$AA40,0) -> 0.72405555 | V40: 10 | W40: 6 | X40: 23 | Y40: =+((V40)+(W40/60)+(X40/3600)) -> 10.106389 | Z40: =+IFERROR(Y40/$AA40,0) -> 0.27594445 | AA40: =+Y40+T40 -> 36.624722 | AC40: =+IFERROR((AA40/P40),0) -> 3.6624722 | AD40: =+IFERROR($O40/$P40,0) -> 42.6 | AE40: =+IFERROR(O40/T40,0) -> 16.064358 | AF40: =+IFERROR(AA40/(P40*$AE$8),0) -> 0.45780903 | AG40: =+P40/$C$8 -> 0.33333333 | AH40: =+Y40*($AI$8*$AH$8) -> 35.372361
B41: Magnex | C41: Zona Energy | D41: ENEL 6054 Zona V OPEX SOT SOC-GA | J41: NPY797 | L41: ✔️ | M41: =data!J8 -> 30 | N41: 24510 | O41: 727 | P41: 11 | Q41: 35 | R41: 58 | S41: 6 | T41: =+((Q41)+(R41/60)+(S41/3600)) -> 35.968333 | U41: =IFERROR(T41/$AA41,0) -> 0.65706254 | V41: 18 | W41: 46 | X41: 22 | Y41: =+((V41)+(W41/60)+(X41/3600)) -> 18.772778 | Z41: =+IFERROR(Y41/$AA41,0) -> 0.34293746 | AA41: =+Y41+T41 -> 54.741111 | AC41: =+IFERROR((AA41/P41),0) -> 4.9764646 | AD41: =+IFERROR($O41/$P41,0) -> 66.090909 | AE41: =+IFERROR(O41/T41,0) -> 20.212224 | AF41: =+IFERROR(AA41/(P41*$AE$8),0) -> 0.62205808 | AG41: =+P41/$C$8 -> 0.36666667 | AH41: =+Y41*($AI$8*$AH$8) -> 65.704722
B42: Magnex | C42: Zona Energy | D42: ENEL 6054 Zona V OPEX SOT SOC-GA | J42: WNN254 | L42: ✔️ | M42: =data!J8 -> 30 | N42: 76569 | O42: 529 | P42: 13 | Q42: 32 | R42: 26 | S42: 16 | T42: =+((Q42)+(R42/60)+(S42/3600)) -> 32.437778 | U42: =IFERROR(T42/$AA42,0) -> 0.39066494 | V42: 50 | W42: 35 | X42: 40 | Y42: =+((V42)+(W42/60)+(X42/3600)) -> 50.594444 | Z42: =+IFERROR(Y42/$AA42,0) -> 0.60933506 | AA42: =+Y42+T42 -> 83.032222 | AC42: =+IFERROR((AA42/P42),0) -> 6.387094 | AD42: =+IFERROR($O42/$P42,0) -> 40.692308 | AE42: =+IFERROR(O42/T42,0) -> 16.308146 | AF42: =+IFERROR(AA42/(P42*$AE$8),0) -> 0.79838675 | AG42: =+P42/$C$8 -> 0.43333333 | AH42: =+Y42*($AI$8*$AH$8) -> 177.08056
B43: Magnex | C43: Zona Energy | D43: ENEL 6054 Zona V OPEX SOT SOC-GA | J43: PMV839 | L43: ✔️ | M43: =data!J8 -> 30 | N43: 14400 | O43: 460 | P43: 10 | Q43: 20 | R43: 38 | S43: 48 | T43: =+((Q43)+(R43/60)+(S43/3600)) -> 20.646667 | U43: =IFERROR(T43/$AA43,0) -> 0.91389507 | V43: 1 | W43: 56 | X43: 43 | Y43: =+((V43)+(W43/60)+(X43/3600)) -> 1.9452778 | Z43: =+IFERROR(Y43/$AA43,0) -> 0.086104929 | AA43: =+Y43+T43 -> 22.591944 | AC43: =+IFERROR((AA43/P43),0) -> 2.2591944 | AD43: =+IFERROR($O43/$P43,0) -> 46 | AE43: =+IFERROR(O43/T43,0) -> 22.279625 | AF43: =+IFERROR(AA43/(P43*$AE$8),0) -> 0.28239931 | AG43: =+P43/$C$8 -> 0.33333333 | AH43: =+Y43*($AI$8*$AH$8) -> 6.8084722
B44: Magnex | C44: Zona Energy | D44: ENEL 6054 Zona V OPEX SOT SOC-GA | J44: NPY966 | L44: ✔️ | M44: =data!J8 -> 30 | N44: 22609 | O44: 116 | P44: 8 | Q44: 9 | R44: 2 | S44: 31 | T44: =+((Q44)+(R44/60)+(S44/3600)) -> 9.0419444 | U44: =IFERROR(T44/$AA44,0) -> 0.69996129 | V44: 3 | W44: 52 | X44: 33 | Y44: =+((V44)+(W44/60)+(X44/3600)) -> 3.8758333 | Z44: =+IFERROR(Y44/$AA44,0) -> 0.30003871 | AA44: =+Y44+T44 -> 12.917778 | AC44: =+IFERROR((AA44/P44),0) -> 1.6147222 | AD44: =+IFERROR($O44/$P44,0) -> 14.5 | AE44: =+IFERROR(O44/T44,0) -> 12.829099 | AF44: =+IFERROR(AA44/(P44*$AE$8),0) -> 0.20184028 | AG44: =+P44/$C$8 -> 0.26666667 | AH44: =+Y44*($AI$8*$AH$8) -> 13.565417
B45: Magnex | C45: Zona Energy | D45: ENEL 6054 Zona V OPEX SOT SOC-GA | J45: PMV833 | L45: ✔️ | M45: =data!J8 -> 30 | N45: 13745 | O45: 467 | P45: 10 | Q45: 23 | R45: 36 | S45: 14 | T45: =+((Q45)+(R45/60)+(S45/3600)) -> 23.603889 | U45: =IFERROR(T45/$AA45,0) -> 0.72098015 | V45: 9 | W45: 8 | X45: 5 | Y45: =+((V45)+(W45/60)+(X45/3600)) -> 9.1347222 | Z45: =+IFERROR(Y45/$AA45,0) -> 0.27901985 | AA45: =+Y45+T45 -> 32.738611 | AC45: =+IFERROR((AA45/P45),0) -> 3.2738611 | AD45: =+IFERROR($O45/$P45,0) -> 46.7 | AE45: =+IFERROR(O45/T45,0) -> 19.784875 | AF45: =+IFERROR(AA45/(P45*$AE$8),0) -> 0.40923264 | AG45: =+P45/$C$8 -> 0.33333333 | AH45: =+Y45*($AI$8*$AH$8) -> 31.971528
B46: Magnex | C46: Zona Energy | D46: ENEL 6054 Zona V OPEX SOT SOC-GA | J46: LMM822 | L46: ✔️ | M46: =data!J8 -> 30 | N46: 348313 | O46: 332 | P46: 15 | Q46: 21 | R46: 1 | S46: 45 | T46: =+((Q46)+(R46/60)+(S46/3600)) -> 21.029167 | U46: =IFERROR(T46/$AA46,0) -> 0.4565355 | V46: 25 | W46: 2 | X46: 0 | Y46: =+((V46)+(W46/60)+(X46/3600)) -> 25.033333 | Z46: =+IFERROR(Y46/$AA46,0) -> 0.5434645 | AA46: =+Y46+T46 -> 46.0625 | AC46: =+IFERROR((AA46/P46),0) -> 3.0708333 | AD46: =+IFERROR($O46/$P46,0) -> 22.133333 | AE46: =+IFERROR(O46/T46,0) -> 15.787597 | AF46: =+IFERROR(AA46/(P46*$AE$8),0) -> 0.38385417 | AG46: =+P46/$C$8 -> 0.5 | AH46: =+Y46*($AI$8*$AH$8) -> 87.616667
B47: Magnex | C47: Zona Energy | D47: ENEL 6054 Zona V OPEX SOT SOC-GA | J47: PMW018 | L47: ✔️ | M47: =data!J8 -> 30 | N47: 14296 | O47: 433 | P47: 11 | Q47: 18 | R47: 56 | S47: 28 | T47: =+((Q47)+(R47/60)+(S47/3600)) -> 18.941111 | U47: =IFERROR(T47/$AA47,0) -> 0.75452574 | V47: 6 | W47: 9 | X47: 44 | Y47: =+((V47)+(W47/60)+(X47/3600)) -> 6.1622222 | Z47: =+IFERROR(Y47/$AA47,0) -> 0.24547426 | AA47: =+Y47+T47 -> 25.103333 | AC47: =+IFERROR((AA47/P47),0) -> 2.2821212 | AD47: =+IFERROR($O47/$P47,0) -> 39.363636 | AE47: =+IFERROR(O47/T47,0) -> 22.860327 | AF47: =+IFERROR(AA47/(P47*$AE$8),0) -> 0.28526515 | AG47: =+P47/$C$8 -> 0.36666667 | AH47: =+Y47*($AI$8*$AH$8) -> 21.567778
B48: Magnex | C48: Zona Energy | D48: ENEL 6054 Zona V OPEX SOT SOC-GA | J48: NPY991 | L48: ✔️ | M48: =data!J8 -> 30 | N48: 25281 | O48: 1334 | P48: 12 | Q48: 50 | R48: 56 | S48: 11 | T48: =+((Q48)+(R48/60)+(S48/3600)) -> 50.936389 | U48: =IFERROR(T48/$AA48,0) -> 0.84117839 | V48: 9 | W48: 37 | X48: 2 | Y48: =+((V48)+(W48/60)+(X48/3600)) -> 9.6172222 | Z48: =+IFERROR(Y48/$AA48,0) -> 0.15882161 | AA48: =+Y48+T48 -> 60.553611 | AC48: =+IFERROR((AA48/P48),0) -> 5.0461343 | AD48: =+IFERROR($O48/$P48,0) -> 111.16667 | AE48: =+IFERROR(O48/T48,0) -> 26.189528 | AF48: =+IFERROR(AA48/(P48*$AE$8),0) -> 0.63076678 | AG48: =+P48/$C$8 -> 0.4 | AH48: =+Y48*($AI$8*$AH$8) -> 33.660278
B49: Magnex | C49: Zona Energy | D49: ENEL 6054 Zona V OPEX SOT SOC-GA | J49: LWL497 | L49: ✔️ | M49: =data!J8 -> 30 | N49: 183477 | O49: 330 | P49: 10 | Q49: 17 | R49: 19 | S49: 23 | T49: =+((Q49)+(R49/60)+(S49/3600)) -> 17.323056 | U49: =IFERROR(T49/$AA49,0) -> 0.4890602 | V49: 18 | W49: 5 | X49: 53 | Y49: =+((V49)+(W49/60)+(X49/3600)) -> 18.098056 | Z49: =+IFERROR(Y49/$AA49,0) -> 0.5109398 | AA49: =+Y49+T49 -> 35.421111 | AC49: =+IFERROR((AA49/P49),0) -> 3.5421111 | AD49: =+IFERROR($O49/$P49,0) -> 33 | AE49: =+IFERROR(O49/T49,0) -> 19.049757 | AF49: =+IFERROR(AA49/(P49*$AE$8),0) -> 0.44276389 | AG49: =+P49/$C$8 -> 0.33333333 | AH49: =+Y49*($AI$8*$AH$8) -> 63.343194
B50: Magnex | C50: Zona Energy | D50: ENEL 6054 Zona V OPEX SOT SOC-GA | J50: NPY799 | L50: ✔️ | M50: =data!J8 -> 30 | N50: 15456 | O50: 378 | P50: 14 | Q50: 17 | R50: 45 | S50: 3 | T50: =+((Q50)+(R50/60)+(S50/3600)) -> 17.750833 | U50: =IFERROR(T50/$AA50,0) -> 0.84941248 | V50: 3 | W50: 8 | X50: 49 | Y50: =+((V50)+(W50/60)+(X50/3600)) -> 3.1469444 | Z50: =+IFERROR(Y50/$AA50,0) -> 0.15058752 | AA50: =+Y50+T50 -> 20.897778 | AC50: =+IFERROR((AA50/P50),0) -> 1.4926984 | AD50: =+IFERROR($O50/$P50,0) -> 27 | AE50: =+IFERROR(O50/T50,0) -> 21.294775 | AF50: =+IFERROR(AA50/(P50*$AE$8),0) -> 0.1865873 | AG50: =+P50/$C$8 -> 0.46666667 | AH50: =+Y50*($AI$8*$AH$8) -> 11.014306
B51: Magnex | C51: Zona Energy | D51: ENEL 6053 Zona III OPEX SOT SOC-GA | J51: NPY796 | L51: ✔️ | M51: =data!J8 -> 30 | N51: 12945 | O51: 353 | P51: 13 | Q51: 24 | R51: 12 | S51: 31 | T51: =+((Q51)+(R51/60)+(S51/3600)) -> 24.208611 | U51: =IFERROR(T51/$AA51,0) -> 0.54995267 | V51: 19 | W51: 48 | X51: 39 | Y51: =+((V51)+(W51/60)+(X51/3600)) -> 19.810833 | Z51: =+IFERROR(Y51/$AA51,0) -> 0.45004733 | AA51: =+Y51+T51 -> 44.019444 | AC51: =+IFERROR((AA51/P51),0) -> 3.3861111 | AD51: =+IFERROR($O51/$P51,0) -> 27.153846 | AE51: =+IFERROR(O51/T51,0) -> 14.581588 | AF51: =+IFERROR(AA51/(P51*$AE$8),0) -> 0.42326389 | AG51: =+P51/$C$8 -> 0.43333333 | AH51: =+Y51*($AI$8*$AH$8) -> 69.337917
B52: Magnex | C52: Zona Energy | D52: ENEL 6053 Zona III OPEX SOT SOC-GA | J52: NPY981 | L52: ✔️ | M52: =data!J8 -> 30 | N52: 14982 | O52: 2 | P52: 6 | Q52: 0 | R52: 55 | S52: 24 | T52: =+((Q52)+(R52/60)+(S52/3600)) -> 0.92333333 | U52: =IFERROR(T52/$AA52,0) -> 0.29549293 | V52: 2 | W52: 12 | X52: 5 | Y52: =+((V52)+(W52/60)+(X52/3600)) -> 2.2013889 | Z52: =+IFERROR(Y52/$AA52,0) -> 0.70450707 | AA52: =+Y52+T52 -> 3.1247222 | AC52: =+IFERROR((AA52/P52),0) -> 0.52078704 | AD52: =+IFERROR($O52/$P52,0) -> 0.33333333 | AE52: =+IFERROR(O52/T52,0) -> 2.166065 | AF52: =+IFERROR(AA52/(P52*$AE$8),0) -> 0.06509838 | AG52: =+P52/$C$8 -> 0.2 | AH52: =+Y52*($AI$8*$AH$8) -> 7.7048611
B53: Magnex | C53: Zona Energy | D53: ENEL 6053 Zona III OPEX SOT SOC-GA | J53: NPY786 | L53: ✔️ | M53: =data!J8 -> 30 | N53: 15508 | O53: 411 | P53: 11 | Q53: 33 | R53: 0 | S53: 25 | T53: =+((Q53)+(R53/60)+(S53/3600)) -> 33.006944 | U53: =IFERROR(T53/$AA53,0) -> 0.61377184 | V53: 20 | W53: 46 | X53: 13 | Y53: =+((V53)+(W53/60)+(X53/3600)) -> 20.770278 | Z53: =+IFERROR(Y53/$AA53,0) -> 0.38622816 | AA53: =+Y53+T53 -> 53.777222 | AC53: =+IFERROR((AA53/P53),0) -> 4.8888384 | AD53: =+IFERROR($O53/$P53,0) -> 37.363636 | AE53: =+IFERROR(O53/T53,0) -> 12.451925 | AF53: =+IFERROR(AA53/(P53*$AE$8),0) -> 0.6111048 | AG53: =+P53/$C$8 -> 0.36666667 | AH53: =+Y53*($AI$8*$AH$8) -> 72.695972
B54: Magnex | C54: Zona Energy | D54: ENEL 6053 Zona III OPEX SOT SOC-GA | J54: NPY972 | L54: ✔️ | M54: =data!J8 -> 30 | N54: 27075 | O54: 753 | P54: 14 | Q54: 43 | R54: 33 | S54: 59 | T54: =+((Q54)+(R54/60)+(S54/3600)) -> 43.566389 | U54: =IFERROR(T54/$AA54,0) -> 0.7961613 | V54: 11 | W54: 9 | X54: 15 | Y54: =+((V54)+(W54/60)+(X54/3600)) -> 11.154167 | Z54: =+IFERROR(Y54/$AA54,0) -> 0.2038387 | AA54: =+Y54+T54 -> 54.720556 | AC54: =+IFERROR((AA54/P54),0) -> 3.9086111 | AD54: =+IFERROR($O54/$P54,0) -> 53.785714 | AE54: =+IFERROR(O54/T54,0) -> 17.283966 | AF54: =+IFERROR(AA54/(P54*$AE$8),0) -> 0.48857639 | AG54: =+P54/$C$8 -> 0.46666667 | AH54: =+Y54*($AI$8*$AH$8) -> 39.039583
B55: Magnex | C55: Zona Generación | D55: GENERACION TELLO | J55: NPY791 | L55: ✔️ | M55: =data!J8 -> 30 | N55: 10463 | O55: 339 | P55: 11 | Q55: 28 | R55: 52 | S55: 17 | T55: =+((Q55)+(R55/60)+(S55/3600)) -> 28.871389 | U55: =IFERROR(T55/$AA55,0) -> 0.62282852 | V55: 17 | W55: 29 | X55: 2 | Y55: =+((V55)+(W55/60)+(X55/3600)) -> 17.483889 | Z55: =+IFERROR(Y55/$AA55,0) -> 0.37717148 | AA55: =+Y55+T55 -> 46.355278 | AC55: =+IFERROR((AA55/P55),0) -> 4.2141162 | AD55: =+IFERROR($O55/$P55,0) -> 30.818182 | AE55: =+IFERROR(O55/T55,0) -> 11.741728 | AF55: =+IFERROR(AA55/(P55*$AE$8),0) -> 0.52676452 | AG55: =+P55/$C$8 -> 0.36666667 | AH55: =+Y55*($AI$8*$AH$8) -> 61.193611
B56: Magnex | C56: Zona Energy | D56: ENEL 6053 Zona III OPEX SOT SOC-GA | J56: NPY789 | L56: ✔️ | M56: =data!J8 -> 30 | N56: 12156 | O56: 493 | P56: 14 | Q56: 31 | R56: 10 | S56: 13 | T56: =+((Q56)+(R56/60)+(S56/3600)) -> 31.170278 | U56: =IFERROR(T56/$AA56,0) -> 0.57395312 | V56: 23 | W56: 8 | X56: 16 | Y56: =+((V56)+(W56/60)+(X56/3600)) -> 23.137778 | Z56: =+IFERROR(Y56/$AA56,0) -> 0.42604688 | AA56: =+Y56+T56 -> 54.308056 | AC56: =+IFERROR((AA56/P56),0) -> 3.8791468 | AD56: =+IFERROR($O56/$P56,0) -> 35.214286 | AE56: =+IFERROR(O56/T56,0) -> 15.816349 | AF56: =+IFERROR(AA56/(P56*$AE$8),0) -> 0.48489335 | AG56: =+P56/$C$8 -> 0.46666667 | AH56: =+Y56*($AI$8*$AH$8) -> 80.982222
B57: Magnex | C57: Zona Energy | D57: ENEL 6053 Zona III OPEX SOT SOC-GA | J57: NPY793 | L57: ✔️ | M57: =data!J8 -> 30 | N57: 9200 | O57: 259 | P57: 14 | Q57: 19 | R57: 17 | S57: 11 | T57: =+((Q57)+(R57/60)+(S57/3600)) -> 19.286389 | U57: =IFERROR(T57/$AA57,0) -> 0.79697651 | V57: 4 | W57: 54 | X57: 47 | Y57: =+((V57)+(W57/60)+(X57/3600)) -> 4.9130556 | Z57: =+IFERROR(Y57/$AA57,0) -> 0.20302349 | AA57: =+Y57+T57 -> 24.199444 | AC57: =+IFERROR((AA57/P57),0) -> 1.7285317 | AD57: =+IFERROR($O57/$P57,0) -> 18.5 | AE57: =+IFERROR(O57/T57,0) -> 13.42916 | AF57: =+IFERROR(AA57/(P57*$AE$8),0) -> 0.21606647 | AG57: =+P57/$C$8 -> 0.46666667 | AH57: =+Y57*($AI$8*$AH$8) -> 17.195694
B58: Magnex | C58: Zona Energy | D58: ENEL 6053 Zona III OPEX SOT SOC-GA | J58: NPY790 | L58: ✔️ | M58: =data!J8 -> 30 | N58: 9581 | O58: 60 | P58: 6 | Q58: 5 | R58: 48 | S58: 5 | T58: =+((Q58)+(R58/60)+(S58/3600)) -> 5.8013889 | U58: =IFERROR(T58/$AA58,0) -> 0.5308846 | V58: 5 | W58: 7 | X58: 35 | Y58: =+((V58)+(W58/60)+(X58/3600)) -> 5.1263889 | Z58: =+IFERROR(Y58/$AA58,0) -> 0.4691154 | AA58: =+Y58+T58 -> 10.927778 | AC58: =+IFERROR((AA58/P58),0) -> 1.8212963 | AD58: =+IFERROR($O58/$P58,0) -> 10 | AE58: =+IFERROR(O58/T58,0) -> 10.342351 | AF58: =+IFERROR(AA58/(P58*$AE$8),0) -> 0.22766204 | AG58: =+P58/$C$8 -> 0.2 | AH58: =+Y58*($AI$8*$AH$8) -> 17.942361
B59: Magnex | C59: Zona Energy | D59: ENEL 6053 Zona III OPEX SOT SOC-GA | J59: NPY950 | L59: ✔️ | M59: =data!J8 -> 30 | N59: 10700 | O59: 506 | P59: 14 | Q59: 33 | R59: 32 | S59: 9 | T59: =+((Q59)+(R59/60)+(S59/3600)) -> 33.535833 | U59: =IFERROR(T59/$AA59,0) -> 0.57702124 | V59: 24 | W59: 34 | X59: 59 | Y59: =+((V59)+(W59/60)+(X59/3600)) -> 24.583056 | Z59: =+IFERROR(Y59/$AA59,0) -> 0.42297876 | AA59: =+Y59+T59 -> 58.118889 | AC59: =+IFERROR((AA59/P59),0) -> 4.1513492 | AD59: =+IFERROR($O59/$P59,0) -> 36.142857 | AE59: =+IFERROR(O59/T59,0) -> 15.088338 | AF59: =+IFERROR(AA59/(P59*$AE$8),0) -> 0.51891865 | AG59: =+P59/$C$8 -> 0.46666667 | AH59: =+Y59*($AI$8*$AH$8) -> 86.040694
B60: Magnex | C60: Zona Occidente | D60: CEN 8596 Estac ANDINA - PREVEN-CORREC | J60: NPY787 | L60: ✔️ | M60: =data!J8 -> 30 | N60: 29442 | O60: 421 | P60: 5 | Q60: 11 | R60: 31 | S60: 36 | T60: =+((Q60)+(R60/60)+(S60/3600)) -> 11.526667 | U60: =IFERROR(T60/$AA60,0) -> 0.92051731 | V60: 0 | W60: 59 | X60: 43 | Y60: =+((V60)+(W60/60)+(X60/3600)) -> 0.99527778 | Z60: =+IFERROR(Y60/$AA60,0) -> 0.079482686 | AA60: =+Y60+T60 -> 12.521944 | AC60: =+IFERROR((AA60/P60),0) -> 2.5043889 | AD60: =+IFERROR($O60/$P60,0) -> 84.2 | AE60: =+IFERROR(O60/T60,0) -> 36.524002 | AF60: =+IFERROR(AA60/(P60*$AE$8),0) -> 0.31304861 | AG60: =+P60/$C$8 -> 0.16666667 | AH60: =+Y60*($AI$8*$AH$8) -> 3.4834722
B61: Magnex | C61: Zona Occidente | D61: CEN 8596 Estac LLANOS - PREVEN-CORREC | J61: LHW539 | L61: ✔️ | M61: =data!J8 -> 30 | N61: 116141 | O61: 745 | P61: 8 | Q61: 18 | R61: 33 | S61: 6 | T61: =+((Q61)+(R61/60)+(S61/3600)) -> 18.551667 | U61: =IFERROR(T61/$AA61,0) -> 0.92189829 | V61: 1 | W61: 34 | X61: 18 | Y61: =+((V61)+(W61/60)+(X61/3600)) -> 1.5716667 | Z61: =+IFERROR(Y61/$AA61,0) -> 0.078101706 | AA61: =+Y61+T61 -> 20.123333 | AC61: =+IFERROR((AA61/P61),0) -> 2.5154167 | AD61: =+IFERROR($O61/$P61,0) -> 93.125 | AE61: =+IFERROR(O61/T61,0) -> 40.158117 | AF61: =+IFERROR(AA61/(P61*$AE$8),0) -> 0.31442708 | AG61: =+P61/$C$8 -> 0.26666667 | AH61: =+Y61*($AI$8*$AH$8) -> 5.5008333
B62: Magnex | C62: Zona Energy | D62: ENEL 6053 Zona III OPEX SOT SOC-GA | J62: NPY985 | L62: ✔️ | M62: =data!J8 -> 30 | N62: 11661 | O62: 411 | P62: 12 | Q62: 25 | R62: 17 | S62: 57 | T62: =+((Q62)+(R62/60)+(S62/3600)) -> 25.299167 | U62: =IFERROR(T62/$AA62,0) -> 0.61963466 | V62: 15 | W62: 31 | X62: 48 | Y62: =+((V62)+(W62/60)+(X62/3600)) -> 15.53 | Z62: =+IFERROR(Y62/$AA62,0) -> 0.38036534 | AA62: =+Y62+T62 -> 40.829167 | AC62: =+IFERROR((AA62/P62),0) -> 3.4024306 | AD62: =+IFERROR($O62/$P62,0) -> 34.25 | AE62: =+IFERROR(O62/T62,0) -> 16.245594 | AF62: =+IFERROR(AA62/(P62*$AE$8),0) -> 0.42530382 | AG62: =+P62/$C$8 -> 0.4 | AH62: =+Y62*($AI$8*$AH$8) -> 54.355
B63: Magnex | C63: Zona Energy | D63: ENEL 6053 Zona III OPEX SOT SOC-GA | J63: IDZ623 | L63: ✔️ | M63: =data!J8 -> 30 | N63: 251980 | O63: 226 | P63: 5 | Q63: 10 | R63: 33 | S63: 54 | T63: =+((Q63)+(R63/60)+(S63/3600)) -> 10.565 | U63: =IFERROR(T63/$AA63,0) -> 0.82223231 | V63: 2 | W63: 17 | X63: 3 | Y63: =+((V63)+(W63/60)+(X63/3600)) -> 2.2841667 | Z63: =+IFERROR(Y63/$AA63,0) -> 0.17776769 | AA63: =+Y63+T63 -> 12.849167 | AC63: =+IFERROR((AA63/P63),0) -> 2.5698333 | AD63: =+IFERROR($O63/$P63,0) -> 45.2 | AE63: =+IFERROR(O63/T63,0) -> 21.391387 | AF63: =+IFERROR(AA63/(P63*$AE$8),0) -> 0.32122917 | AG63: =+P63/$C$8 -> 0.16666667 | AH63: =+Y63*($AI$8*$AH$8) -> 7.9945833
B64: Magnex | C64: Zona Energy | D64: ENEL 6053 Zona III OPEX SOT SOC-GA | J64: NPY996 | L64: ✔️ | M64: =data!J8 -> 30 | N64: 11108 | O64: 270 | P64: 7 | Q64: 23 | R64: 15 | S64: 53 | T64: =+((Q64)+(R64/60)+(S64/3600)) -> 23.264722 | U64: =IFERROR(T64/$AA64,0) -> 0.7858671 | V64: 6 | W64: 20 | X64: 21 | Y64: =+((V64)+(W64/60)+(X64/3600)) -> 6.3391667 | Z64: =+IFERROR(Y64/$AA64,0) -> 0.2141329 | AA64: =+Y64+T64 -> 29.603889 | AC64: =+IFERROR((AA64/P64),0) -> 4.229127 | AD64: =+IFERROR($O64/$P64,0) -> 38.571429 | AE64: =+IFERROR(O64/T64,0) -> 11.605554 | AF64: =+IFERROR(AA64/(P64*$AE$8),0) -> 0.52864087 | AG64: =+P64/$C$8 -> 0.23333333 | AH64: =+Y64*($AI$8*$AH$8) -> 22.187083
B65: Magnex | C65: Zona Energy | D65: ENEL 6053 Zona III OPEX SOT SOC-GA | J65: NPY605 | L65: ✔️ | M65: =data!J8 -> 30 | N65: 13604 | O65: 663 | P65: 12 | Q65: 45 | R65: 10 | S65: 32 | T65: =+((Q65)+(R65/60)+(S65/3600)) -> 45.175556 | U65: =IFERROR(T65/$AA65,0) -> 0.58771746 | V65: 31 | W65: 41 | X65: 26 | Y65: =+((V65)+(W65/60)+(X65/3600)) -> 31.690556 | Z65: =+IFERROR(Y65/$AA65,0) -> 0.41228254 | AA65: =+Y65+T65 -> 76.866111 | AC65: =+IFERROR((AA65/P65),0) -> 6.4055093 | AD65: =+IFERROR($O65/$P65,0) -> 55.25 | AE65: =+IFERROR(O65/T65,0) -> 14.676079 | AF65: =+IFERROR(AA65/(P65*$AE$8),0) -> 0.80068866 | AG65: =+P65/$C$8 -> 0.4 | AH65: =+Y65*($AI$8*$AH$8) -> 110.91694
B66: Magnex | C66: Zona Energy | D66: ENEL 6053 Zona III OPEX SOT SOC-GA | J66: NZT850 | L66: ✔️ | M66: =data!J8 -> 30 | N66: 10905 | O66: 244 | P66: 7 | Q66: 13 | R66: 11 | S66: 19 | T66: =+((Q66)+(R66/60)+(S66/3600)) -> 13.188611 | U66: =IFERROR(T66/$AA66,0) -> 0.96694636 | V66: 0 | W66: 27 | X66: 3 | Y66: =+((V66)+(W66/60)+(X66/3600)) -> 0.45083333 | Z66: =+IFERROR(Y66/$AA66,0) -> 0.033053643 | AA66: =+Y66+T66 -> 13.639444 | AC66: =+IFERROR((AA66/P66),0) -> 1.9484921 | AD66: =+IFERROR($O66/$P66,0) -> 34.857143 | AE66: =+IFERROR(O66/T66,0) -> 18.500811 | AF66: =+IFERROR(AA66/(P66*$AE$8),0) -> 0.24356151 | AG66: =+P66/$C$8 -> 0.23333333 | AH66: =+Y66*($AI$8*$AH$8) -> 1.5779167
B67: Magnex | C67: Zona Energy | D67: ENEL 6053 Zona III OPEX SOT SOC-GA | J67: NZT856 | L67: ✔️ | M67: =data!J8 -> 30 | N67: 17528 | O67: 38 | P67: 3 | Q67: 2 | R67: 1 | S67: 39 | T67: =+((Q67)+(R67/60)+(S67/3600)) -> 2.0275 | U67: =IFERROR(T67/$AA67,0) -> 0.9583771 | V67: 0 | W67: 5 | X67: 17 | Y67: =+((V67)+(W67/60)+(X67/3600)) -> 0.088055556 | Z67: =+IFERROR(Y67/$AA67,0) -> 0.041622899 | AA67: =+Y67+T67 -> 2.1155556 | AC67: =+IFERROR((AA67/P67),0) -> 0.70518519 | AD67: =+IFERROR($O67/$P67,0) -> 12.666667 | AE67: =+IFERROR(O67/T67,0) -> 18.742293 | AF67: =+IFERROR(AA67/(P67*$AE$8),0) -> 0.088148148 | AG67: =+P67/$C$8 -> 0.1 | AH67: =+Y67*($AI$8*$AH$8) -> 0.30819444
B68: Magnex | C68: Zona Occidente | D68: CEN 8596 Estac LLANOS - PREVEN-CORREC | J68: LHW559 | L68: ✔️ | M68: =data!J8 -> 30 | N68: 136852 | O68: 777 | P68: 7 | Q68: 28 | R68: 47 | S68: 22 | T68: =+((Q68)+(R68/60)+(S68/3600)) -> 28.789444 | U68: =IFERROR(T68/$AA68,0) -> 0.86011386 | V68: 4 | W68: 40 | X68: 56 | Y68: =+((V68)+(W68/60)+(X68/3600)) -> 4.6822222 | Z68: =+IFERROR(Y68/$AA68,0) -> 0.13988614 | AA68: =+Y68+T68 -> 33.471667 | AC68: =+IFERROR((AA68/P68),0) -> 4.7816667 | AD68: =+IFERROR($O68/$P68,0) -> 111 | AE68: =+IFERROR(O68/T68,0) -> 26.989058 | AF68: =+IFERROR(AA68/(P68*$AE$8),0) -> 0.59770833 | AG68: =+P68/$C$8 -> 0.23333333 | AH68: =+Y68*($AI$8*$AH$8) -> 16.387778
B69: Magnex | C69: Zona Energy | D69: ENEL 6053 Zona III OPEX SOT SOC-GA | J69: PMV837 | L69: ✔️ | M69: =data!J8 -> 30 | N69: 9103 | O69: 156 | P69: 6 | Q69: 12 | R69: 45 | S69: 41 | T69: =+((Q69)+(R69/60)+(S69/3600)) -> 12.761389 | U69: =IFERROR(T69/$AA69,0) -> 0.85346189 | V69: 2 | W69: 11 | X69: 28 | Y69: =+((V69)+(W69/60)+(X69/3600)) -> 2.1911111 | Z69: =+IFERROR(Y69/$AA69,0) -> 0.14653811 | AA69: =+Y69+T69 -> 14.9525 | AC69: =+IFERROR((AA69/P69),0) -> 2.4920833 | AD69: =+IFERROR($O69/$P69,0) -> 26 | AE69: =+IFERROR(O69/T69,0) -> 12.224375 | AF69: =+IFERROR(AA69/(P69*$AE$8),0) -> 0.31151042 | AG69: =+P69/$C$8 -> 0.2 | AH69: =+Y69*($AI$8*$AH$8) -> 7.6688889
B70: Magnex | C70: Zona Energy | D70: ENEL 6053 Zona III OPEX SOT SOC-GA | J70: PMV838 | L70: ✔️ | M70: =data!J8 -> 30 | N70: 9263 | O70: 167 | P70: 7 | Q70: 12 | R70: 54 | S70: 49 | T70: =+((Q70)+(R70/60)+(S70/3600)) -> 12.913611 | U70: =IFERROR(T70/$AA70,0) -> 0.74054192 | V70: 4 | W70: 31 | X70: 28 | Y70: =+((V70)+(W70/60)+(X70/3600)) -> 4.5244444 | Z70: =+IFERROR(Y70/$AA70,0) -> 0.25945808 | AA70: =+Y70+T70 -> 17.438056 | AC70: =+IFERROR((AA70/P70),0) -> 2.4911508 | AD70: =+IFERROR($O70/$P70,0) -> 23.857143 | AE70: =+IFERROR(O70/T70,0) -> 12.932091 | AF70: =+IFERROR(AA70/(P70*$AE$8),0) -> 0.31139385 | AG70: =+P70/$C$8 -> 0.23333333 | AH70: =+Y70*($AI$8*$AH$8) -> 15.835556
B71: Magnex | C71: Zona Energy | D71: ENEL 6053 Zona III OPEX SOT SOC-GA | J71: PMV834 | L71: ✔️ | M71: =data!J8 -> 30 | N71: 8492 | O71: 75 | P71: 7 | Q71: 7 | R71: 42 | S71: 9 | T71: =+((Q71)+(R71/60)+(S71/3600)) -> 7.7025 | U71: =IFERROR(T71/$AA71,0) -> 0.71503352 | V71: 3 | W71: 4 | X71: 11 | Y71: =+((V71)+(W71/60)+(X71/3600)) -> 3.0697222 | Z71: =+IFERROR(Y71/$AA71,0) -> 0.28496648 | AA71: =+Y71+T71 -> 10.772222 | AC71: =+IFERROR((AA71/P71),0) -> 1.5388889 | AD71: =+IFERROR($O71/$P71,0) -> 10.714286 | AE71: =+IFERROR(O71/T71,0) -> 9.7370983 | AF71: =+IFERROR(AA71/(P71*$AE$8),0) -> 0.19236111 | AG71: =+P71/$C$8 -> 0.23333333 | AH71: =+Y71*($AI$8*$AH$8) -> 10.744028
B72: Magnex | C72: Zona Energy | D72: ENEL 6053 Zona III OPEX SOT SOC-GA | J72: PMV832 | L72: ✔️ | M72: =data!J8 -> 30 | N72: 8193 | O72: 115 | P72: 5 | Q72: 11 | R72: 10 | S72: 16 | T72: =+((Q72)+(R72/60)+(S72/3600)) -> 11.171111 | U72: =IFERROR(T72/$AA72,0) -> 0.78870367 | V72: 2 | W72: 59 | X72: 34 | Y72: =+((V72)+(W72/60)+(X72/3600)) -> 2.9927778 | Z72: =+IFERROR(Y72/$AA72,0) -> 0.21129633 | AA72: =+Y72+T72 -> 14.163889 | AC72: =+IFERROR((AA72/P72),0) -> 2.8327778 | AD72: =+IFERROR($O72/$P72,0) -> 23 | AE72: =+IFERROR(O72/T72,0) -> 10.29441 | AF72: =+IFERROR(AA72/(P72*$AE$8),0) -> 0.35409722 | AG72: =+P72/$C$8 -> 0.16666667 | AH72: =+Y72*($AI$8*$AH$8) -> 10.474722
B73: Magnex | C73: Zona Energy | D73: ENEL 6053 Zona III OPEX SOT SOC-GA | J73: WOP059 | L73: ✔️ | M73: =data!J8 -> 30 | N73: 137878 | O73: 136 | P73: 8 | Q73: 10 | R73: 59 | S73: 16 | T73: =+((Q73)+(R73/60)+(S73/3600)) -> 10.987778 | U73: =IFERROR(T73/$AA73,0) -> 0.56127705 | V73: 8 | W73: 35 | X73: 19 | Y73: =+((V73)+(W73/60)+(X73/3600)) -> 8.5886111 | Z73: =+IFERROR(Y73/$AA73,0) -> 0.43872295 | AA73: =+Y73+T73 -> 19.576389 | AC73: =+IFERROR((AA73/P73),0) -> 2.4470486 | AD73: =+IFERROR($O73/$P73,0) -> 17 | AE73: =+IFERROR(O73/T73,0) -> 12.377389 | AF73: =+IFERROR(AA73/(P73*$AE$8),0) -> 0.30588108 | AG73: =+P73/$C$8 -> 0.26666667 | AH73: =+Y73*($AI$8*$AH$8) -> 30.060139
B74: Magnex | C74: Zona Energy | D74: ENEL 6053 Zona III OPEX SOT SOC-GA | J74: WOO967 | L74: ✔️ | M74: =data!J8 -> 30 | N74: 178617 | O74: 193 | P74: 8 | Q74: 14 | R74: 38 | S74: 44 | T74: =+((Q74)+(R74/60)+(S74/3600)) -> 14.645556 | U74: =IFERROR(T74/$AA74,0) -> 0.51011543 | V74: 14 | W74: 3 | X74: 53 | Y74: =+((V74)+(W74/60)+(X74/3600)) -> 14.064722 | Z74: =+IFERROR(Y74/$AA74,0) -> 0.48988457 | AA74: =+Y74+T74 -> 28.710278 | AC74: =+IFERROR((AA74/P74),0) -> 3.5887847 | AD74: =+IFERROR($O74/$P74,0) -> 24.125 | AE74: =+IFERROR(O74/T74,0) -> 13.178059 | AF74: =+IFERROR(AA74/(P74*$AE$8),0) -> 0.44859809 | AG74: =+P74/$C$8 -> 0.26666667 | AH74: =+Y74*($AI$8*$AH$8) -> 49.226528
B75: Magnex | C75: Zona Energy | D75: ENEL 6053 Zona III OPEX SOT SOC-GA | J75: PPK445 | L75: ✔️ | M75: =data!J8 -> 30 | N75: 4954 | O75: 151 | P75: 8 | Q75: 15 | R75: 42 | S75: 42 | T75: =+((Q75)+(R75/60)+(S75/3600)) -> 15.711667 | U75: =IFERROR(T75/$AA75,0) -> 0.38410659 | V75: 25 | W75: 11 | X75: 34 | Y75: =+((V75)+(W75/60)+(X75/3600)) -> 25.192778 | Z75: =+IFERROR(Y75/$AA75,0) -> 0.61589341 | AA75: =+Y75+T75 -> 40.904444 | AC75: =+IFERROR((AA75/P75),0) -> 5.1130556 | AD75: =+IFERROR($O75/$P75,0) -> 18.875 | AE75: =+IFERROR(O75/T75,0) -> 9.6106927 | AF75: =+IFERROR(AA75/(P75*$AE$8),0) -> 0.63913194 | AG75: =+P75/$C$8 -> 0.26666667 | AH75: =+Y75*($AI$8*$AH$8) -> 88.174722
B76: Magnex | C76: Zona Energy | D76: ENEL 6053 Zona III OPEX SOT SOC-GA | J76: WLS449 | L76: ✔️ | M76: =data!J8 -> 30 | N76: 132986 | O76: 136 | P76: 7 | Q76: 12 | R76: 44 | S76: 40 | T76: =+((Q76)+(R76/60)+(S76/3600)) -> 12.744444 | U76: =IFERROR(T76/$AA76,0) -> 0.49687019 | V76: 12 | W76: 54 | X76: 18 | Y76: =+((V76)+(W76/60)+(X76/3600)) -> 12.905 | Z76: =+IFERROR(Y76/$AA76,0) -> 0.50312981 | AA76: =+Y76+T76 -> 25.649444 | AC76: =+IFERROR((AA76/P76),0) -> 3.6642063 | AD76: =+IFERROR($O76/$P76,0) -> 19.428571 | AE76: =+IFERROR(O76/T76,0) -> 10.671316 | AF76: =+IFERROR(AA76/(P76*$AE$8),0) -> 0.45802579 | AG76: =+P76/$C$8 -> 0.23333333 | AH76: =+Y76*($AI$8*$AH$8) -> 45.1675
B77: Magnex | C77: Zona Energy | D77: ENEL 6053 Zona III OPEX SOT SOC-GA | J77: WOP108 | L77: ✔️ | M77: =data!J8 -> 30 | N77: 202931 | O77: 128 | P77: 7 | Q77: 12 | R77: 2 | S77: 57 | T77: =+((Q77)+(R77/60)+(S77/3600)) -> 12.049167 | U77: =IFERROR(T77/$AA77,0) -> 0.42466934 | V77: 16 | W77: 19 | X77: 26 | Y77: =+((V77)+(W77/60)+(X77/3600)) -> 16.323889 | Z77: =+IFERROR(Y77/$AA77,0) -> 0.57533066 | AA77: =+Y77+T77 -> 28.373056 | AC77: =+IFERROR((AA77/P77),0) -> 4.0532937 | AD77: =+IFERROR($O77/$P77,0) -> 18.285714 | AE77: =+IFERROR(O77/T77,0) -> 10.623141 | AF77: =+IFERROR(AA77/(P77*$AE$8),0) -> 0.50666171 | AG77: =+P77/$C$8 -> 0.23333333 | AH77: =+Y77*($AI$8*$AH$8) -> 57.133611
B78: Magnex | C78: Zona Energy | D78: ENEL 6053 Zona III OPEX SOT SOC-GA | J78: WOP279 | L78: ✔️ | M78: =data!J8 -> 30 | N78: 112948 | O78: 96 | P78: 6 | Q78: 8 | R78: 27 | S78: 10 | T78: =+((Q78)+(R78/60)+(S78/3600)) -> 8.4527778 | U78: =IFERROR(T78/$AA78,0) -> 0.28956959 | V78: 20 | W78: 44 | X78: 17 | Y78: =+((V78)+(W78/60)+(X78/3600)) -> 20.738056 | Z78: =+IFERROR(Y78/$AA78,0) -> 0.71043041 | AA78: =+Y78+T78 -> 29.190833 | AC78: =+IFERROR((AA78/P78),0) -> 4.8651389 | AD78: =+IFERROR($O78/$P78,0) -> 16 | AE78: =+IFERROR(O78/T78,0) -> 11.357213 | AF78: =+IFERROR(AA78/(P78*$AE$8),0) -> 0.60814236 | AG78: =+P78/$C$8 -> 0.2 | AH78: =+Y78*($AI$8*$AH$8) -> 72.583194
B79: Magnex | C79: Zona Energy | D79: ENEL 6053 Zona III OPEX SOT SOC-GA | J79: PMV831 | L79: ✔️ | M79: =data!J8 -> 30 | N79: 8915 | O79: 145 | P79: 7 | Q79: 11 | R79: 24 | S79: 19 | T79: =+((Q79)+(R79/60)+(S79/3600)) -> 11.405278 | U79: =IFERROR(T79/$AA79,0) -> 0.70442809 | V79: 4 | W79: 47 | X79: 8 | Y79: =+((V79)+(W79/60)+(X79/3600)) -> 4.7855556 | Z79: =+IFERROR(Y79/$AA79,0) -> 0.29557191 | AA79: =+Y79+T79 -> 16.190833 | AC79: =+IFERROR((AA79/P79),0) -> 2.3129762 | AD79: =+IFERROR($O79/$P79,0) -> 20.714286 | AE79: =+IFERROR(O79/T79,0) -> 12.713412 | AF79: =+IFERROR(AA79/(P79*$AE$8),0) -> 0.28912202 | AG79: =+P79/$C$8 -> 0.23333333 | AH79: =+Y79*($AI$8*$AH$8) -> 16.749444
B80: Magnex | C80: Zona Energy | D80: ENEL 6053 Zona III OPEX SOT SOC-GA | J80: PMV836 | L80: ✔️ | M80: =data!J8 -> 30 | N80: 8258 | O80: 138 | P80: 6 | Q80: 11 | R80: 5 | S80: 35 | T80: =+((Q80)+(R80/60)+(S80/3600)) -> 11.093056 | U80: =IFERROR(T80/$AA80,0) -> 0.76427697 | V80: 3 | W80: 25 | X80: 17 | Y80: =+((V80)+(W80/60)+(X80/3600)) -> 3.4213889 | Z80: =+IFERROR(Y80/$AA80,0) -> 0.23572303 | AA80: =+Y80+T80 -> 14.514444 | AC80: =+IFERROR((AA80/P80),0) -> 2.4190741 | AD80: =+IFERROR($O80/$P80,0) -> 23 | AE80: =+IFERROR(O80/T80,0) -> 12.440215 | AF80: =+IFERROR(AA80/(P80*$AE$8),0) -> 0.30238426 | AG80: =+P80/$C$8 -> 0.2 | AH80: =+Y80*($AI$8*$AH$8) -> 11.974861
B81: Magnex | C81: Zona Energy | D81: ENEL 6053 Zona III OPEX SOT SOC-GA | J81: WOP088 | L81: ⚠️ | M81: =data!J8 -> 30 | N81: 5614 | O81: 125 | P81: 7 | Q81: 12 | R81: 11 | S81: 34 | T81: =+((Q81)+(R81/60)+(S81/3600)) -> 12.192778 | U81: =IFERROR(T81/$AA81,0) -> 0.3190481 | V81: 26 | W81: 1 | X81: 24 | Y81: =+((V81)+(W81/60)+(X81/3600)) -> 26.023333 | Z81: =+IFERROR(Y81/$AA81,0) -> 0.6809519 | AA81: =+Y81+T81 -> 38.216111 | AC81: =+IFERROR((AA81/P81),0) -> 5.4594444 | AD81: =+IFERROR($O81/$P81,0) -> 17.857143 | AE81: =+IFERROR(O81/T81,0) -> 10.251971 | AF81: =+IFERROR(AA81/(P81*$AE$8),0) -> 0.68243056 | AG81: =+P81/$C$8 -> 0.23333333 | AH81: =+Y81*($AI$8*$AH$8) -> 91.081667
B82: Magnex | C82: Zona Energy | D82: ENEL 6053 Zona III OPEX SOT SOC-GA | J82: GKV610 | L82: ✔️ | M82: =data!J8 -> 30 | N82: 174346 | O82: 244 | P82: 9 | Q82: 19 | R82: 40 | S82: 27 | T82: =+((Q82)+(R82/60)+(S82/3600)) -> 19.674167 | U82: =IFERROR(T82/$AA82,0) -> 0.37141703 | V82: 33 | W82: 17 | X82: 47 | Y82: =+((V82)+(W82/60)+(X82/3600)) -> 33.296389 | Z82: =+IFERROR(Y82/$AA82,0) -> 0.62858297 | AA82: =+Y82+T82 -> 52.970556 | AC82: =+IFERROR((AA82/P82),0) -> 5.8856173 | AD82: =+IFERROR($O82/$P82,0) -> 27.111111 | AE82: =+IFERROR(O82/T82,0) -> 12.40205 | AF82: =+IFERROR(AA82/(P82*$AE$8),0) -> 0.73570216 | AG82: =+P82/$C$8 -> 0.3 | AH82: =+Y82*($AI$8*$AH$8) -> 116.53736
B83: Magnex | C83: Zona Occidente | D83: CEN 8596 Estac LLANOS - PREVEN-CORREC | J83: LHW470 | L83: ✔️ | M83: =data!J8 -> 30 | N83: 110956 | O83: 792 | P83: 8 | Q83: 25 | R83: 53 | S83: 54 | T83: =+((Q83)+(R83/60)+(S83/3600)) -> 25.898333 | U83: =IFERROR(T83/$AA83,0) -> 0.85948966 | V83: 4 | W83: 14 | X83: 2 | Y83: =+((V83)+(W83/60)+(X83/3600)) -> 4.2338889 | Z83: =+IFERROR(Y83/$AA83,0) -> 0.14051034 | AA83: =+Y83+T83 -> 30.132222 | AC83: =+IFERROR((AA83/P83),0) -> 3.7665278 | AD83: =+IFERROR($O83/$P83,0) -> 99 | AE83: =+IFERROR(O83/T83,0) -> 30.581118 | AF83: =+IFERROR(AA83/(P83*$AE$8),0) -> 0.47081597 | AG83: =+P83/$C$8 -> 0.26666667 | AH83: =+Y83*($AI$8*$AH$8) -> 14.818611
B84: Magnex | C84: Zona Energy | D84: ENEL 6053 Zona III OPEX SOT SOC-GA | J84: NPY982 | L84: ✔️ | M84: =data!J8 -> 30 | N84: 12730 | O84: 119 | P84: 7 | Q84: 9 | R84: 25 | S84: 39 | T84: =+((Q84)+(R84/60)+(S84/3600)) -> 9.4275 | U84: =IFERROR(T84/$AA84,0) -> 0.91197098 | V84: 0 | W84: 54 | X84: 36 | Y84: =+((V84)+(W84/60)+(X84/3600)) -> 0.91 | Z84: =+IFERROR(Y84/$AA84,0) -> 0.088029021 | AA84: =+Y84+T84 -> 10.3375 | AC84: =+IFERROR((AA84/P84),0) -> 1.4767857 | AD84: =+IFERROR($O84/$P84,0) -> 17 | AE84: =+IFERROR(O84/T84,0) -> 12.622647 | AF84: =+IFERROR(AA84/(P84*$AE$8),0) -> 0.18459821 | AG84: =+P84/$C$8 -> 0.23333333 | AH84: =+Y84*($AI$8*$AH$8) -> 3.185
B85: Magnex | C85: Zona Energy | D85: ENEL 6053 Zona III OPEX SOT SOC-GA | J85: NPY632 | L85: ✔️ | M85: =data!J8 -> 30 | N85: 8361 | O85: 181 | P85: 8 | Q85: 16 | R85: 42 | S85: 11 | T85: =+((Q85)+(R85/60)+(S85/3600)) -> 16.703056 | U85: =IFERROR(T85/$AA85,0) -> 0.44750982 | V85: 20 | W85: 37 | X85: 17 | Y85: =+((V85)+(W85/60)+(X85/3600)) -> 20.621389 | Z85: =+IFERROR(Y85/$AA85,0) -> 0.55249018 | AA85: =+Y85+T85 -> 37.324444 | AC85: =+IFERROR((AA85/P85),0) -> 4.6655556 | AD85: =+IFERROR($O85/$P85,0) -> 22.625 | AE85: =+IFERROR(O85/T85,0) -> 10.836341 | AF85: =+IFERROR(AA85/(P85*$AE$8),0) -> 0.58319444 | AG85: =+P85/$C$8 -> 0.26666667 | AH85: =+Y85*($AI$8*$AH$8) -> 72.174861
B86: Magnex | C86: Zona Energy | D86: ENEL 6053 Zona III OPEX SOT SOC-GA | J86: NPY975 | L86: ✔️ | M86: =data!J8 -> 30 | N86: 17668 | O86: 625 | P86: 10 | Q86: 40 | R86: 48 | S86: 34 | T86: =+((Q86)+(R86/60)+(S86/3600)) -> 40.809444 | U86: =IFERROR(T86/$AA86,0) -> 0.49469658 | V86: 41 | W86: 41 | X86: 4 | Y86: =+((V86)+(W86/60)+(X86/3600)) -> 41.684444 | Z86: =+IFERROR(Y86/$AA86,0) -> 0.50530342 | AA86: =+Y86+T86 -> 82.493889 | AC86: =+IFERROR((AA86/P86),0) -> 8.2493889 | AD86: =+IFERROR($O86/$P86,0) -> 62.5 | AE86: =+IFERROR(O86/T86,0) -> 15.315082 | AF86: =+IFERROR(AA86/(P86*$AE$8),0) -> 1.0311736 | AG86: =+P86/$C$8 -> 0.33333333 | AH86: =+Y86*($AI$8*$AH$8) -> 145.89556
B87: Magnex | C87: Zona Energy | D87: ENEL 6053 Zona III OPEX SOT SOC-GA | J87: NPY992 | L87: ✔️ | M87: =data!J8 -> 30 | N87: 7452 | O87: 206 | P87: 8 | Q87: 19 | R87: 36 | S87: 17 | T87: =+((Q87)+(R87/60)+(S87/3600)) -> 19.604722 | U87: =IFERROR(T87/$AA87,0) -> 0.72668396 | V87: 7 | W87: 22 | X87: 25 | Y87: =+((V87)+(W87/60)+(X87/3600)) -> 7.3736111 | Z87: =+IFERROR(Y87/$AA87,0) -> 0.27331604 | AA87: =+Y87+T87 -> 26.978333 | AC87: =+IFERROR((AA87/P87),0) -> 3.3722917 | AD87: =+IFERROR($O87/$P87,0) -> 25.75 | AE87: =+IFERROR(O87/T87,0) -> 10.507672 | AF87: =+IFERROR(AA87/(P87*$AE$8),0) -> 0.42153646 | AG87: =+P87/$C$8 -> 0.26666667 | AH87: =+Y87*($AI$8*$AH$8) -> 25.807639
B88: Magnex | C88: Zona Energy | D88: ENEL 6053 Zona III OPEX SOT SOC-GA | J88: NPY788 | L88: ✔️ | M88: =data!J8 -> 30 | N88: 12522 | O88: 121 | P88: 7 | Q88: 10 | R88: 20 | S88: 6 | T88: =+((Q88)+(R88/60)+(S88/3600)) -> 10.335 | U88: =IFERROR(T88/$AA88,0) -> 0.43162914 | V88: 13 | W88: 36 | X88: 33 | Y88: =+((V88)+(W88/60)+(X88/3600)) -> 13.609167 | Z88: =+IFERROR(Y88/$AA88,0) -> 0.56837086 | AA88: =+Y88+T88 -> 23.944167 | AC88: =+IFERROR((AA88/P88),0) -> 3.4205952 | AD88: =+IFERROR($O88/$P88,0) -> 17.285714 | AE88: =+IFERROR(O88/T88,0) -> 11.707789 | AF88: =+IFERROR(AA88/(P88*$AE$8),0) -> 0.4275744 | AG88: =+P88/$C$8 -> 0.23333333 | AH88: =+Y88*($AI$8*$AH$8) -> 47.632083
B89: Magnex | C89: Zona Energy | D89: ENEL 6053 Zona III OPEX SOT SOC-GA | J89: NPY670 | L89: ✔️ | M89: =data!J8 -> 30 | N89: 9213 | O89: 283 | P89: 8 | Q89: 20 | R89: 31 | S89: 7 | T89: =+((Q89)+(R89/60)+(S89/3600)) -> 20.518611 | U89: =IFERROR(T89/$AA89,0) -> 0.79473882 | V89: 5 | W89: 17 | X89: 58 | Y89: =+((V89)+(W89/60)+(X89/3600)) -> 5.2994444 | Z89: =+IFERROR(Y89/$AA89,0) -> 0.20526118 | AA89: =+Y89+T89 -> 25.818056 | AC89: =+IFERROR((AA89/P89),0) -> 3.2272569 | AD89: =+IFERROR($O89/$P89,0) -> 35.375 | AE89: =+IFERROR(O89/T89,0) -> 13.792357 | AF89: =+IFERROR(AA89/(P89*$AE$8),0) -> 0.40340712 | AG89: =+P89/$C$8 -> 0.26666667 | AH89: =+Y89*($AI$8*$AH$8) -> 18.548056
B90: Magnex | C90: Zona Energy | D90: ENEL 6053 Zona III OPEX SOT SOC-GA | J90: NPY690 | L90: ✔️ | M90: =data!J8 -> 30 | N90: 10430 | O90: 118 | P90: 7 | Q90: 10 | R90: 39 | S90: 12 | T90: =+((Q90)+(R90/60)+(S90/3600)) -> 10.653333 | U90: =IFERROR(T90/$AA90,0) -> 0.67036059 | V90: 5 | W90: 14 | X90: 19 | Y90: =+((V90)+(W90/60)+(X90/3600)) -> 5.2386111 | Z90: =+IFERROR(Y90/$AA90,0) -> 0.32963941 | AA90: =+Y90+T90 -> 15.891944 | AC90: =+IFERROR((AA90/P90),0) -> 2.2702778 | AD90: =+IFERROR($O90/$P90,0) -> 16.857143 | AE90: =+IFERROR(O90/T90,0) -> 11.076345 | AF90: =+IFERROR(AA90/(P90*$AE$8),0) -> 0.28378472 | AG90: =+P90/$C$8 -> 0.23333333 | AH90: =+Y90*($AI$8*$AH$8) -> 18.335139
B91: Magnex | C91: Zona Energy | D91: ENEL 6053 Zona III OPEX SOT SOC-GA | J91: NPY993 | L91: ✔️ | M91: =data!J8 -> 30 | N91: 1627 | O91: 256 | P91: 8 | Q91: 16 | R91: 43 | S91: 21 | T91: =+((Q91)+(R91/60)+(S91/3600)) -> 16.7225 | U91: =IFERROR(T91/$AA91,0) -> 0.94529324 | V91: 0 | W91: 58 | X91: 4 | Y91: =+((V91)+(W91/60)+(X91/3600)) -> 0.96777778 | Z91: =+IFERROR(Y91/$AA91,0) -> 0.05470676 | AA91: =+Y91+T91 -> 17.690278 | AC91: =+IFERROR((AA91/P91),0) -> 2.2112847 | AD91: =+IFERROR($O91/$P91,0) -> 32 | AE91: =+IFERROR(O91/T91,0) -> 15.308716 | AF91: =+IFERROR(AA91/(P91*$AE$8),0) -> 0.27641059 | AG91: =+P91/$C$8 -> 0.26666667 | AH91: =+Y91*($AI$8*$AH$8) -> 3.3872222
B92: Magnex | C92: Zona Energy | D92: ENEL 6053 Zona III OPEX SOT SOC-GA | J92: NPY967 | L92: ✔️ | M92: =data!J8 -> 30 | N92: 15656 | O92: 279 | P92: 7 | Q92: 17 | R92: 47 | S92: 9 | T92: =+((Q92)+(R92/60)+(S92/3600)) -> 17.785833 | U92: =IFERROR(T92/$AA92,0) -> 0.43678075 | V92: 22 | W92: 56 | X92: 4 | Y92: =+((V92)+(W92/60)+(X92/3600)) -> 22.934444 | Z92: =+IFERROR(Y92/$AA92,0) -> 0.56321925 | AA92: =+Y92+T92 -> 40.720278 | AC92: =+IFERROR((AA92/P92),0) -> 5.8171825 | AD92: =+IFERROR($O92/$P92,0) -> 39.857143 | AE92: =+IFERROR(O92/T92,0) -> 15.686642 | AF92: =+IFERROR(AA92/(P92*$AE$8),0) -> 0.72714782 | AG92: =+P92/$C$8 -> 0.23333333 | AH92: =+Y92*($AI$8*$AH$8) -> 80.270556
B93: Magnex | C93: Zona Energy | D93: ENEL 6053 Zona III OPEX SOT SOC-GA | J93: NPY780 | L93: ✔️ | M93: =data!J8 -> 30 | N93: 11433 | O93: 240 | P93: 7 | Q93: 21 | R93: 39 | S93: 38 | T93: =+((Q93)+(R93/60)+(S93/3600)) -> 21.660556 | U93: =IFERROR(T93/$AA93,0) -> 0.69381618 | V93: 9 | W93: 33 | X93: 32 | Y93: =+((V93)+(W93/60)+(X93/3600)) -> 9.5588889 | Z93: =+IFERROR(Y93/$AA93,0) -> 0.30618382 | AA93: =+Y93+T93 -> 31.219444 | AC93: =+IFERROR((AA93/P93),0) -> 4.4599206 | AD93: =+IFERROR($O93/$P93,0) -> 34.285714 | AE93: =+IFERROR(O93/T93,0) -> 11.080048 | AF93: =+IFERROR(AA93/(P93*$AE$8),0) -> 0.55749008 | AG93: =+P93/$C$8 -> 0.23333333 | AH93: =+Y93*($AI$8*$AH$8) -> 33.456111
B94: Magnex | C94: Zona Energy | D94: ENEL 6053 Zona III OPEX SOT SOC-GA | J94: NPY631 | L94: ✔️ | M94: =data!J8 -> 30 | N94: 12694 | O94: 2 | P94: 7 | Q94: 0 | R94: 42 | S94: 27 | T94: =+((Q94)+(R94/60)+(S94/3600)) -> 0.7075 | U94: =IFERROR(T94/$AA94,0) -> 0.2638558 | V94: 1 | W94: 58 | X94: 26 | Y94: =+((V94)+(W94/60)+(X94/3600)) -> 1.9738889 | Z94: =+IFERROR(Y94/$AA94,0) -> 0.7361442 | AA94: =+Y94+T94 -> 2.6813889 | AC94: =+IFERROR((AA94/P94),0) -> 0.38305556 | AD94: =+IFERROR($O94/$P94,0) -> 0.28571429 | AE94: =+IFERROR(O94/T94,0) -> 2.8268551 | AF94: =+IFERROR(AA94/(P94*$AE$8),0) -> 0.047881944 | AG94: =+P94/$C$8 -> 0.23333333 | AH94: =+Y94*($AI$8*$AH$8) -> 6.9086111
B95: Magnex | C95: Zona Energy | D95: ENEL 6053 Zona III OPEX SOT SOC-GA | J95: NPY970 | L95: ✔️ | M95: =data!J8 -> 30 | N95: 11234 | O95: 156 | P95: 7 | Q95: 12 | R95: 11 | S95: 49 | T95: =+((Q95)+(R95/60)+(S95/3600)) -> 12.196944 | U95: =IFERROR(T95/$AA95,0) -> 0.51962699 | V95: 11 | W95: 16 | X95: 32 | Y95: =+((V95)+(W95/60)+(X95/3600)) -> 11.275556 | Z95: =+IFERROR(Y95/$AA95,0) -> 0.48037301 | AA95: =+Y95+T95 -> 23.4725 | AC95: =+IFERROR((AA95/P95),0) -> 3.3532143 | AD95: =+IFERROR($O95/$P95,0) -> 22.285714 | AE95: =+IFERROR(O95/T95,0) -> 12.790089 | AF95: =+IFERROR(AA95/(P95*$AE$8),0) -> 0.41915179 | AG95: =+P95/$C$8 -> 0.23333333 | AH95: =+Y95*($AI$8*$AH$8) -> 39.464444
B96: Magnex | C96: Zona Energy | D96: ENEL 6053 Zona III OPEX SOT SOC-GA | J96: NPZ067 | L96: ✔️ | M96: =data!J8 -> 30 | N96: 9745 | O96: 237 | P96: 10 | Q96: 17 | R96: 22 | S96: 10 | T96: =+((Q96)+(R96/60)+(S96/3600)) -> 17.369444 | U96: =IFERROR(T96/$AA96,0) -> 0.77917061 | V96: 4 | W96: 55 | X96: 22 | Y96: =+((V96)+(W96/60)+(X96/3600)) -> 4.9227778 | Z96: =+IFERROR(Y96/$AA96,0) -> 0.22082939 | AA96: =+Y96+T96 -> 22.292222 | AC96: =+IFERROR((AA96/P96),0) -> 2.2292222 | AD96: =+IFERROR($O96/$P96,0) -> 23.7 | AE96: =+IFERROR(O96/T96,0) -> 13.644651 | AF96: =+IFERROR(AA96/(P96*$AE$8),0) -> 0.27865278 | AG96: =+P96/$C$8 -> 0.33333333 | AH96: =+Y96*($AI$8*$AH$8) -> 17.229722
B97: Magnex | C97: Zona Energy | D97: ENEL 6053 Zona III OPEX SOT SOC-GA | J97: NPY963 | L97: ✔️ | M97: =data!J8 -> 30 | N97: 14678 | O97: 457 | P97: 10 | Q97: 28 | R97: 24 | S97: 8 | T97: =+((Q97)+(R97/60)+(S97/3600)) -> 28.402222 | U97: =IFERROR(T97/$AA97,0) -> 0.38200132 | V97: 45 | W97: 56 | X97: 56 | Y97: =+((V97)+(W97/60)+(X97/3600)) -> 45.948889 | Z97: =+IFERROR(Y97/$AA97,0) -> 0.61799868 | AA97: =+Y97+T97 -> 74.351111 | AC97: =+IFERROR((AA97/P97),0) -> 7.4351111 | AD97: =+IFERROR($O97/$P97,0) -> 45.7 | AE97: =+IFERROR(O97/T97,0) -> 16.09029 | AF97: =+IFERROR(AA97/(P97*$AE$8),0) -> 0.92938889 | AG97: =+P97/$C$8 -> 0.33333333 | AH97: =+Y97*($AI$8*$AH$8) -> 160.82111
B98: Magnex | C98: Zona Energy | D98: ENEL 6053 Zona III OPEX SOT SOC-GA | J98: NPY795 | L98: ✔️ | M98: =data!J8 -> 30 | N98: 12311 | O98: 182 | P98: 6 | Q98: 15 | R98: 30 | S98: 8 | T98: =+((Q98)+(R98/60)+(S98/3600)) -> 15.502222 | U98: =IFERROR(T98/$AA98,0) -> 0.53859888 | V98: 13 | W98: 16 | X98: 49 | Y98: =+((V98)+(W98/60)+(X98/3600)) -> 13.280278 | Z98: =+IFERROR(Y98/$AA98,0) -> 0.46140112 | AA98: =+Y98+T98 -> 28.7825 | AC98: =+IFERROR((AA98/P98),0) -> 4.7970833 | AD98: =+IFERROR($O98/$P98,0) -> 30.333333 | AE98: =+IFERROR(O98/T98,0) -> 11.740252 | AF98: =+IFERROR(AA98/(P98*$AE$8),0) -> 0.59963542 | AG98: =+P98/$C$8 -> 0.2 | AH98: =+Y98*($AI$8*$AH$8) -> 46.480972
B99: Magnex | C99: Zona Energy | D99: ENEL 6053 Zona III OPEX SOT SOC-GA | J99: NZT989 | L99: ✔️ | M99: =data!J8 -> 30 | N99: 10865 | O99: 122 | P99: 7 | Q99: 9 | R99: 36 | S99: 34 | T99: =+((Q99)+(R99/60)+(S99/3600)) -> 9.6094444 | U99: =IFERROR(T99/$AA99,0) -> 0.8285988 | V99: 1 | W99: 59 | X99: 16 | Y99: =+((V99)+(W99/60)+(X99/3600)) -> 1.9877778 | Z99: =+IFERROR(Y99/$AA99,0) -> 0.1714012 | AA99: =+Y99+T99 -> 11.597222 | AC99: =+IFERROR((AA99/P99),0) -> 1.656746 | AD99: =+IFERROR($O99/$P99,0) -> 17.428571 | AE99: =+IFERROR(O99/T99,0) -> 12.695843 | AF99: =+IFERROR(AA99/(P99*$AE$8),0) -> 0.20709325 | AG99: =+P99/$C$8 -> 0.23333333 | AH99: =+Y99*($AI$8*$AH$8) -> 6.9572222
B100: Magnex | C100: Zona Cerrejón | D100: CERREJON 2022 Cabinas-GA | J100: NPY469 | L100: ✔️ | M100: =data!J8 -> 30 | N100: 75335 | O100: 930 | P100: 7 | Q100: 33 | R100: 25 | S100: 16 | T100: =+((Q100)+(R100/60)+(S100/3600)) -> 33.421111 | U100: =IFERROR(T100/$AA100,0) -> 0.52572797 | V100: 30 | W100: 9 | X100: 0 | Y100: =+((V100)+(W100/60)+(X100/3600)) -> 30.15 | Z100: =+IFERROR(Y100/$AA100,0) -> 0.47427203 | AA100: =+Y100+T100 -> 63.571111 | AC100: =+IFERROR((AA100/P100),0) -> 9.0815873 | AD100: =+IFERROR($O100/$P100,0) -> 132.85714 | AE100: =+IFERROR(O100/T100,0) -> 27.826723 | AF100: =+IFERROR(AA100/(P100*$AE$8),0) -> 1.1351984 | AG100: =+P100/$C$8 -> 0.23333333 | AH100: =+Y100*($AI$8*$AH$8) -> 105.525
B101: Magnex | C101: Zona Cerrejón | D101: CERREJON 2022 Cabinas-GA | J101: NPY474 | L101: ✔️ | M101: =data!J8 -> 30 | N101: 95402 | O101: 909 | P101: 7 | Q101: 33 | R101: 9 | S101: 57 | T101: =+((Q101)+(R101/60)+(S101/3600)) -> 33.165833 | U101: =IFERROR(T101/$AA101,0) -> 0.6158675 | V101: 20 | W101: 41 | X101: 11 | Y101: =+((V101)+(W101/60)+(X101/3600)) -> 20.686389 | Z101: =+IFERROR(Y101/$AA101,0) -> 0.3841325 | AA101: =+Y101+T101 -> 53.852222 | AC101: =+IFERROR((AA101/P101),0) -> 7.6931746 | AD101: =+IFERROR($O101/$P101,0) -> 129.85714 | AE101: =+IFERROR(O101/T101,0) -> 27.407724 | AF101: =+IFERROR(AA101/(P101*$AE$8),0) -> 0.96164683 | AG101: =+P101/$C$8 -> 0.23333333 | AH101: =+Y101*($AI$8*$AH$8) -> 72.402361
B102: Magnex | C102: Zona Cerrejón | D102: CERREJON 2022 Cabinas-GA | J102: NPY475 | L102: ⚠️ | M102: =data!J8 -> 30 | N102: 75278 | O102: 1 | P102: 5 | Q102: 0 | R102: 29 | S102: 21 | T102: =+((Q102)+(R102/60)+(S102/3600)) -> 0.48916667 | U102: =IFERROR(T102/$AA102,0) -> 0.36972496 | V102: 0 | W102: 50 | X102: 2 | Y102: =+((V102)+(W102/60)+(X102/3600)) -> 0.83388889 | Z102: =+IFERROR(Y102/$AA102,0) -> 0.63027504 | AA102: =+Y102+T102 -> 1.3230556 | AC102: =+IFERROR((AA102/P102),0) -> 0.26461111 | AD102: =+IFERROR($O102/$P102,0) -> 0.2 | AE102: =+IFERROR(O102/T102,0) -> 2.044293 | AF102: =+IFERROR(AA102/(P102*$AE$8),0) -> 0.033076389 | AG102: =+P102/$C$8 -> 0.16666667 | AH102: =+Y102*($AI$8*$AH$8) -> 2.9186111
...

Sheet parámetros
B2: Distancia total recorrida
B3: 90 | C3: días | F3: 60 | G3: días | J3: 30 | K3: días | N3: 7 | O3: días
B4: Q1 | C4: 0 | D4: 200 | E4: Menos de 200 | F4: Q1 | G4: 0 | H4: =+$F$3*D4/$B$3 -> 133.33333 | I4: Menos de 133 | J4: Q1 | K4: 0 | L4: =+$J$3*H4/$F$3 -> 66.666667 | M4: Menos de 67 | N4: Q1 | O4: 0 | P4: =+$N$3*L4/$J$3 -> 15.555556 | Q4: Menos de 16
B5: Q2 | C5: =+D4 -> 200 | D5: 500 | E5: 200 a 500 | F5: Q2 | G5: =+H4 -> 133.33333 | H5: =+$F$3*D5/$B$3 -> 333.33333 | I5: 133 a 333 | J5: Q2 | K5: =+L4 -> 66.666667 | L5: =+$J$3*H5/$F$3 -> 166.66667 | M5: 67 a 167 | N5: Q2 | O5: =+P4 -> 15.555556 | P5: =+$N$3*L5/$J$3 -> 38.888889 | Q5: 16 a 39
B6: Q3 | C6: =+D5 -> 500 | D6: 1500 | E6: 500 a 1,500 | F6: Q3 | G6: =+H5 -> 333.33333 | H6: =+$F$3*D6/$B$3 -> 1000 | I6: 333 a 1,000 | J6: Q3 | K6: =+L5 -> 166.66667 | L6: =+$J$3*H6/$F$3 -> 500 | M6: 167 a 500 | N6: Q3 | O6: =+P5 -> 38.888889 | P6: =+$N$3*L6/$J$3 -> 116.66667 | Q6: 39 a 117
B7: Q4 | C7: =+D6 -> 1500 | D7: 3000 | E7: 1,500 a 3,000 | F7: Q4 | G7: =+H6 -> 1000 | H7: =+$F$3*D7/$B$3 -> 2000 | I7: 1,000 a 2,000 | J7: Q4 | K7: =+L6 -> 500 | L7: =+$J$3*H7/$F$3 -> 1000 | M7: 500 a 1,000 | N7: Q4 | O7: =+P6 -> 116.66667 | P7: =+$N$3*L7/$J$3 -> 233.33333 | Q7: 117 a 233
B8: Q5 | C8: =+D7 -> 3000 | E8: Más de 3,000 | F8: Q5 | G8: =+H7 -> 2000 | I8: Más de 2,000 | J8: Q5 | K8: =+L7 -> 1000 | M8: Más de 1,000 | N8: Q5 | O8: =+P7 -> 233.33333 | Q8: Más de 233
B10: Total de días conducidos
B11: 90 | C11: días | F11: 60 | G11: días | J11: 30 | K11: días | N11: 7 | O11: días
B12: Q1 | C12: 0 | D12: =+B11*0.2 -> 18 | E12: Menos de 18 | F12: Q1 | G12: 0 | H12: =+F11*0.2 -> 12 | I12: Menos de 12 | J12: Q1 | K12: 0 | L12: =+J11*0.2 -> 6 | M12: Menos de 6 | N12: Q1 | O12: 0 | P12: =+N11*0.2 -> 1.4 | Q12: Menos de 1
B13: Q2 | C13: =+D12 -> 18 | D13: =+B11*0.4 -> 36 | E13: 18 a 36 | F13: Q2 | G13: =+H12 -> 12 | H13: =+F11*0.4 -> 24 | I13: 12 a 24 | J13: Q2 | K13: =+L12 -> 6 | L13: =+J11*0.4 -> 12 | M13: 6 a 12 | N13: Q2 | O13: =+P12 -> 1.4 | P13: =+N11*0.4 -> 2.8 | Q13: 1 a 3
B14: Q3 | C14: =+D13 -> 36 | D14: =+B11*0.6 -> 54 | E14: 36 a 54 | F14: Q3 | G14: =+H13 -> 24 | H14: =+F11*0.6 -> 36 | I14: 24 a 36 | J14: Q3 | K14: =+L13 -> 12 | L14: =+J11*0.6 -> 18 | M14: 12 a 18 | N14: Q3 | O14: =+P13 -> 2.8 | P14: =+N11*0.6 -> 4.2 | Q14: 3 a 4
B15: Q4 | C15: =+D14 -> 54 | D15: =+B11*0.8 -> 72 | E15: 54 a 72 | F15: Q4 | G15: =+H14 -> 36 | H15: =+F11*0.8 -> 48 | I15: 36 a 48 | J15: Q4 | K15: =+L14 -> 18 | L15: =+J11*0.8 -> 24 | M15: 18 a 24 | N15: Q4 | O15: =+P14 -> 4.2 | P15: =+N11*0.8 -> 5.6 | Q15: 4 a 6
B16: Q5 | C16: =+D15 -> 72 | D16: =+B11 -> 90 | E16: 72 a 90 | F16: Q5 | G16: =+H15 -> 48 | H16: =+F11 -> 60 | I16: 48 a 60 | J16: Q5 | K16: =+L15 -> 24 | L16: =+J11 -> 30 | M16: 24 a 30 | N16: Q5 | O16: =+P15 -> 5.6 | P16: =+N11 -> 7 | Q16: 6 a 7
C21: Km | D21: =+D22*3.78541 -> 1 | E21: Litros
C22: Millas | D22: 0.26417218 | E22: Galones

Sheet Grupo 1
A1: Grupo | B1: Vehículos | C1: GPS sin conexión 5+ días | D1: Días conducidos (promedio) | E1: Kilómetros conducidos (promedio) | F1: Horas conducidas (promedio) | G1: Tiempo en ralentí (promedio) | H1: % de utilización (días conducidos)
A2: Magnex | B2: 209 | C2: 0 | D2: 9 | E2: 679 | F2: 32:19:22 | G2: 15:37:08 | H2: 27%

Sheet Grupo 2
A1: Grupo 1 | B1: Grupo | C1: Vehículos | D1: GPS sin conexión 5+ días | E1: Días conducidos (promedio) | F1: Kilómetros conducidos (promedio) | G1: Horas conducidas (promedio) | H1: Tiempo en ralentí (promedio) | I1: % de utilización (días conducidos)
A2: Magnex | B2: Asset Information | C2: 209 | D2: 0 | E2: 9 | F2: 679 | G2: 32:19:22 | H2: 15:37:08 | I2: 27%
A3: Magnex | B3: CALIBRATION SERVICES | C3: 0 | D3: 0 | E3: 0 | F3: 0 | G3: 0:00:00 | H3: 0:00:00 | I3: -
A4: Magnex | B4: Zona Centro | C4: 2 | D4: 0 | E4: 23 | F4: 2073 | G4: 54:05:01 | H4: 4:54:22 | I4: 75%
A5: Magnex | B5: Zona Cerrejón | C5: 50 | D5: 0 | E5: 4 | F5: 473 | G5: 16:47:56 | H5: 11:15:25 | I5: 13%
A6: Magnex | B6: Zona Drummond | C6: 48 | D6: 0 | E6: 4 | F6: 353 | G6: 14:17:26 | H6: 12:43:29 | I6: 11%
A7: Magnex | B7: Zona Energy | C7: 78 | D7: 0 | E7: 11 | F7: 486 | G7: 26:55:31 | H7: 15:27:22 | I7: 33%
A8: Magnex | B8: Zona Generación | C8: 17 | D8: 0 | E8: 25 | F8: 3162 | G8: 165:36:32 | H8: 48:53:50 | I8: 84%
A9: Magnex | B9: Zona Occidente | C9: 12 | D9: 0 | E9: 5 | F9: 367 | G9: 12:14:57 | H9: 1:29:27 | I9: 14%
A10: Magnex | B10: Zona Tabarca | C10: 0 | D10: 0 | E10: 0 | F10: 0 | G10: 0:00:00 | H10: 0:00:00 | I10: -

Sheet Grupo 3
A1: Grupo 1 | B1: Grupo 2 | C1: Grupo | D1: Vehículos | E1: GPS sin conexión 5+ días | F1: Días conducidos (promedio) | G1: Kilómetros conducidos (promedio) | H1: Horas conducidas (promedio) | I1: Tiempo en ralentí (promedio) | J1: % de utilización (días conducidos)
A2: Magnex | B2: Asset Information | C2: Asset Purpose | D2: 0 | E2: 0 | F2: 0 | G2: 0 | H2: 0:00:00 | I2: 0:00:00 | J2: -
A3: Magnex | B3: Asset Information | C3: Asset Type | D3: 209 | E3: 0 | F3: 9 | G3: 679 | H3: 32:19:22 | I3: 15:37:08 | J3: 27%
A4: Magnex | B4: Zona Centro | C4: Campos Menores RegCentral | D4: 0 | E4: 0 | F4: 0 | G4: 0 | H4: 0:00:00 | I4: 0:00:00 | J4: -
A5: Magnex | B5: Zona Occidente | C5: CEN 8596 Estac ANDINA - PREVEN-CORREC | D5: 8 | E5: 0 | F5: 4 | G5: 262 | H5: 9:13:01 | I5: 0:55:32 | J5: 13%
A6: Magnex | B6: Zona Occidente | C6: CEN 8596 Estac CAÑO LIMON - MOH | D6: 0 | E6: 0 | F6: 0 | G6: 0 | H6: 0:00:00 | I6: 0:00:00 | J6: -
A7: Magnex | B7: Zona Occidente | C7: CEN 8596 Estac CAÑO LIMON-PREVEN-CORREC | D7: 0 | E7: 0 | F7: 0 | G7: 0 | H7: 0:00:00 | I7: 0:00:00 | J7: -
A8: Magnex | B8: Zona Occidente | C8: CEN 8596 Estac LLANOS - PREVEN-CORREC | D8: 4 | E8: 0 | F8: 6 | G8: 579 | H8: 18:18:48 | I8: 2:37:19 | J8: 18%
A9: Magnex | B9: Zona Occidente | C9: CEN 8596 Estac SUR - PREVEN - CORREC | D9: 0 | E9: 0 | F9: 0 | G9: 0 | H9: 0:00:00 | I9: 0:00:00 | J9: -
A10: Magnex | B10: Zona Cerrejón | C10: CERREJON 0174 Bombas-GA | D10: 13 | E10: 0 | F10: 4 | G10: 489 | H10: 16:30:53 | I10: 11:57:48 | J10: 12%
A11: Magnex | B11: Zona Cerrejón | C11: CERREJON 2022 Cabinas-GA | D11: 22 | E11: 0 | F11: 5 | G11: 515 | H11: 18:25:31 | I11: 12:01:49 | J11: 15%
A12: Magnex | B12: Zona Cerrejón | C12: CERREJON 3534 Soldadura-GA | D12: 14 | E12: 0 | F12: 4 | G12: 390 | H12: 14:42:47 | I12: 9:57:17 | J12: 11%
A13: Magnex | B13: Zona Drummond | C13: DRUMMOND 1547 Liviano-GA | D13: 5 | E13: 0 | F13: 4 | G13: 427 | H13: 15:23:04 | I13: 8:25:17 | J13: 11%
... A35: Magnex | B35: Zona Centro | C35: TRANSVERSAL IND | D35: 0 | E35: 0 | F35: 0 | G35: 0 | H35: 0:00:00 | I35: 0:00:00 | J35: -

Sheet Grupo 4
A1: Grupo 1 | B1: Grupo 2 | C1: Grupo 3 | D1: Grupo | E1: Vehículos | F1: GPS sin conexión 5+ días | G1: Días conducidos (promedio) | H1: Kilómetros conducidos (promedio) | I1: Horas conducidas (promedio) | J1: Tiempo en ralentí (promedio) | K1: % de utilización (días conducidos)
A2: Magnex | B2: Asset Information | C2: Asset Type | D2: Container | E2: 0 | F2: 0 | G2: 0 | H2: 0 | I2: 0:00:00 | J2: 0:00:00 | K2: -
A3: Magnex | B3: Asset Information | C3: Powertrain and Fuel Type | D3: Electric or Plug-In Hybrid | E3: 0 | F3: 0 | G3: 0 | H3: 0 | I3: 0:00:00 | J3: 0:00:00 | K3: -
A4: Magnex | B4: Asset Information | C4: Asset Type | D4: Equipment | E4: 0 | F4: 0 | G4: 0 | H4: 0 | I4: 0:00:00 | J4: 0:00:00 | K4: -
A5: Magnex | B5: Asset Information | C5: Powertrain and Fuel Type | D5: Fuel Cell Electric Vehicle | E5: 0 | F5: 0 | G5: 0 | H5: 0 | I5: 0:00:00 | J5: 0:00:00 | K5: -
A6: Magnex | B6: Asset Information | C6: Powertrain and Fuel Type | D6: Internal Combustion Engine | E6: 202 | F6: 0 | G6: 9 | H6: 699 | I6: 33:18:52 | J6: 16:01:05 | K6: 27%
A7: Magnex | B7: Asset Information | C7: Powertrain and Fuel Type | D7: Manually Classified Powertrain | E7: 15 | F7: 0 | G7: 7 | H7: 717 | I7: 27:26:25 | J7: 9:57:29 | K7: 23%
A8: Magnex | B8: Asset Information | C8: Asset Type | D8: Trailer | E8: 0 | F8: 0 | G8: 0 | H8: 0 | I8: 0:00:00 | J8: 0:00:00 | K8: -
A9: Magnex | B9: Asset Information | C9: Asset Type | D9: Vehicle | E9: 209 | F9: 0 | G9: 9 | H9: 679 | I9: 32:19:22 | J9: 15:37:08 | K9: 27%

Sheet Grupo 5
A1: Grupo 1 | B1: Grupo 2 | C1: Grupo 3 | D1: Grupo 4 | E1: Grupo | F1: Vehículos | G1: GPS sin conexión 5+ días | H1: Días conducidos (promedio) | I1: Kilómetros conducidos (promedio) | J1: Horas conducidas (promedio) | K1: Tiempo en ralentí (promedio) | L1: % de utilización (días conducidos)
A2: Magnex | B2: Asset Information | C2: Powertrain and Fuel Type | D2: Electric or Plug-In Hybrid | E2: Battery Electric Vehicle | F2: 0 | G2: 0 | H2: 0 | I2: 0 | J2: 0:00:00 | K2: 0:00:00 | L2: -
A3: Magnex | B3: Asset Information | C3: Powertrain and Fuel Type | D3: Internal Combustion Engine | E3: Biodiesel | F3: 0 | G3: 0 | H3: 0 | I3: 0 | J3: 0:00:00 | K3: 0:00:00 | L3: -
A4: Magnex | B4: Asset Information | C4: Powertrain and Fuel Type | D4: Internal Combustion Engine | E4: Compressed Natural Gas | F4: 0 | G4: 0 | H4: 0 | I4: 0 | J4: 0:00:00 | K4: 0:00:00 | L4: -
A5: Magnex | B5: Asset Information | C5: Powertrain and Fuel Type | D5: Internal Combustion Engine | E5: Diesel | F5: 197 | G5: 0 | H5: 9 | I5: 711 | J5: 33:49:11 | K5: 16:20:04 | L5: 28%
A6: Magnex | B6: Asset Information | C6: Powertrain and Fuel Type | D6: Internal Combustion Engine | E6: Ethanol | F6: 0 | G6: 0 | H6: 0 | I6: 0 | J6: 0:00:00 | K6: 0:00:00 | L6: -
A7: Magnex | B7: Asset Information | C7: Powertrain and Fuel Type | D7: Internal Combustion Engine | E7: Gasoline or Petrol | F7: 5 | G7: 0 | H7: 6 | I7: 234 | J7: 13:24:45 | K7: 3:33:10 | L7: 18%
A8: Magnex | B8: Asset Information | C8: Powertrain and Fuel Type | D8: Internal Combustion Engine | E8: Other Fuel Type | F8: 0 | G8: 0 | H8: 0 | I8: 0 | J8: 0:00:00 | K8: 0:00:00 | L8: -
A9: Magnex | B9: Asset Information | C9: Powertrain and Fuel Type | D9: Electric or Plug-In Hybrid | E9: Plug-in Hybrid Electric Vehicle | F9: 0 | G9: 0 | H9: 0 | I9: 0 | J9: 0:00:00 | K9: 0:00:00 | L9: -
A10: Magnex | B10: Asset Information | C10: Powertrain and Fuel Type | D10: Internal Combustion Engine | E10: Propane or Liquified Petroleum Gas | F10: 0 | G10: 0 | H10: 0 | I10: 0 | J10: 0:00:00 | K10: 0:00:00 | L10: -

Sheet data
A1: Organización | B1: MAGNEX_COL
A2: Fecha del reporte | B2: =B4 -> 46202
A3: Desde | B3: 46173
A4: Hasta | B4: 46202
A5: Días | B5: =B4-B3+1 -> 30
A6: Unidad de distancia | B6: KM
A7: Grupo 1 | B7: Grupo 2 | C7: Grupo 3 | D7: Grupo 4 | E7: Grupo 5 | F7: Vehículo | G7: Conductor actual | H7: GPS | I7: Odómetro KM | J7: Días conducidos | K7: Kilómetros conducidos | L7: Horas conducidas | M7: Tiempo en ralentí | N7: % de utilización (días conducidos)
A8: Magnex | B8: Zona Generación | C8: ECP 1107 Rubiales Serv. Integrales | F8: QLO286 | H8: ✔️ | I8: 30820 | J8: 30 | K8: 6044 | L8: 324:19:25 | M8: 66:45:57 | N8: 100%
A9: Magnex | B9: Zona Centro | C9: GMA CENTRO | F9: NPY686 | H9: ✔️ | I9: 24050 | J9: 22 | K9: 1208 | L9: 42:03:04 | M9: 6:15:20 | N9: 73%
A10: Magnex | B10: Zona Energy | C10: ENEL 6053 Zona III OPEX SOT SOC-GA | F10: PMV840 | H10: ✔️ | I10: 7510 | J10: 20 | K10: 483 | L10: 37:13:50 | M10: 16:04:40 | N10: 63%
A11: Magnex | B11: Zona Energy | C11: ENEL 6053 Zona III OPEX SOT SOC-GA | F11: NPY798 | H11: ✔️ | I11: 10809 | J11: 26 | K11: 860 | L11: 66:33:51 | M11: 26:01:28 | N11: 83%
A12: Magnex | B12: Zona Energy | C12: ENEL 6054 Zona V OPEX SOT SOC-GA | F12: GSO698 | H12: ✔️ | I12: 138492 | J12: 24 | K12: 3187 | L12: 131:38:31 | M12: 39:19:25 | N12: 80%
A13: Magnex | B13: Zona Energy | C13: ENEL 6054 Zona V OPEX SOT SOC-GA | F13: NPY979 | H13: ✔️ | I13: 20833 | J13: 20 | K13: 1701 | L13: 72:58:59 | M13: 28:08:22 | N13: 67%
A14: Magnex | B14: Zona Energy | C14: ENEL 6054 Zona V OPEX SOT SOC-GA | F14: NPY794 | H14: ✔️ | I14: 21171 | J14: 22 | K14: 1042 | L14: 57:40:03 | M14: 14:56:14 | N14: 67%
A15: Magnex | B15: Zona Energy | C15: ENEL 6054 Zona V OPEX SOT SOC-GA | F15: NPY609 | H15: ✔️ | I15: 18011 | J15: 22 | K15: 1337 | L15: 68:47:36 | M15: 32:43:18 | N15: 67%
A16: Magnex | B16: Zona Energy | C16: ENEL 6054 Zona V OPEX SOT SOC-GA | F16: NPY995 | H16: ✔️ | I16: 18436 | J16: 21 | K16: 1167 | L16: 56:30:46 | M16: 23:14:10 | N16: 60%
A17: Magnex | B17: Zona Energy | C17: ENEL 6054 Zona V OPEX SOT SOC-GA | F17: JSL414 | H17: ✔️ | I17: 168484 | J17: 9 | K17: 338 | L17: 14:33:52 | M17: 11:17:12 | N17: 20%
A18: Magnex | B18: Zona Energy | C18: ENEL 6054 Zona V OPEX SOT SOC-GA | F18: GSN681 | H18: ✔️ | I18: 163678 | J18: 20 | K18: 1858 | L18: 75:50:34 | M18: 23:27:37 | N18: 63%
A19: Magnex | B19: Zona Energy | C19: ENEL 6054 Zona V OPEX SOT SOC-GA | F19: NPY976 | H19: ✔️ | I19: 21065 | J19: 19 | K19: 653 | L19: 34:01:42 | M19: 11:30:51 | N19: 47%
... A168: Magnex | B168: Zona Cerrejón | C168: CERREJON 0174 Bombas-GA | F168: NPY487 | H168: ✔️ | I168: 70991 | J168: 3 | K168: 1 | L168: 1:18:14 | M168: 1:39:30 | N168: 0%
A169: Magnex | B169: Zona Drummond | F169: QNN496 | H169: ✔️ | I169: 12755 | J169: 4 | K169: 579 | L169: 23:59:06 | M169: 18:09:37 | N169: 13%
A170: Magnex | B170: Zona Cerrejón | C170: CERREJON 2022 Cabinas-GA | F170: KSR316 | H170: ✔️ | I170: 134942 | J170: 3 | K170: 268 | L170: 9:24:34 | M170: 1:55:24 | N170: 10%
A171: Magnex | B171: Zona Cerrejón | C171: CERREJON 2022 Cabinas-GA | F171: NPY459 | H171: ✔️ | I171: 78104 | J171: 2 | K171: 296 | L171: 10:16:38 | M171: 3:12:50 | N171: 7%
A172: Magnex | B172: Zona Cerrejón | C172: CERREJON 0174 Bombas-GA | F172: LUX622 | H172: ✔️ | I172: 65825 | J172: 3 | K172: 329 | L172: 10:59:09 | M172: 8:59:05 | N172: 10%
A173: Magnex | B173: Zona Cerrejón | C173: CERREJON 2022 Cabinas-GA | F173: KSR314 | H173: ✔️ | I173: 135782 | J173: 1 | K173: 0 | L173: 0:00:04 | M173: 0:00:00 | N173: 0%
A174: Magnex | B174: Zona Cerrejón | C174: CERREJON 3534 Soldadura-GA | F174: KSP722 | H174: ✔️ | I174: 126089 | J174: 0 | K174: 0 | L174: 0:00:00 | M174: 0:00:00 | N174: 0%
A175: Magnex | B175: Zona Cerrejón | C175: CERREJON 0174 Bombas-GA | F175: NPY489 | H175: ✔️ | I175: 67478 | J175: 1 | K175: 0 | L175: 0:10:18 | M175: 0:15:05 | N175: 0%
A176: Magnex | B176: Zona Drummond | C176: DRUMMOND 1547 Liviano-GA | F176: QNN499 | H176: ✔️ | I176: 11621 | J176: 3 | K176: 442 | L176: 19:10:40 | M176: 20:50:53 | N176: 10%
A177: Magnex | B177: Zona Drummond | C177: DRUMMOND 1859T-1885T Mtto - Limpieza-GA | F177: NPY616 | H177: ✔️ | I177: 76972 | J177: 3 | K177: 408 | L177: 14:01:00 | M177: 16:24:54 | N177: 10%
A178: Magnex | B178: Zona Drummond | C178: DRUMMOND 1859T-1885T Mtto - Limpieza-GA | F178: NPY617 | H178: ✔️ | I178: 80424 | J178: 3 | K178: 370 | L178: 17:33:09 | M178: 23:37:48 | N178: 10%
A179: Magnex | B179: Zona Drummond | C179: DRUMMOND 2314 Soldadura-GA | F179: QLO510 | H179: ✔️ | I179: 4511 | J179: 1 | K179: 22 | L179: 0:42:09 | M179: 0:26:00 | N179: 3%
A180: Magnex | B180: Zona Drummond | C180: DRUMMOND 1859T-1885T Mtto - Limpieza-GA | F180: NPY621 | H180: ✔️ | I180: 74944 | J180: 3 | K180: 437 | L180: 25:34:26 | M180: 19:19:47 | N180: 10%
A181: Magnex | B181: Zona Drummond | C181: DRUMMOND 1859T-1885T Mtto - Limpieza-GA | F181: NPY622 | H181: ✔️ | I181: 76078 | J181: 3 | K181: 509 | L181: 24:06:38 | M181: 11:49:22 | N181: 10%
... A198: Magnex | B198: Zona Centro | C198: GMA CENTRO | F198: NPY672 | H198: ✔️ | I198: 69150 | J198: 23 | K198: 2939 | L198: 66:06:58 | M198: 3:33:25 | N198: 77%
A199: Magnex | B199: Zona Energy | C199: ENEL 6234 Zona X OPEX SOT SOC-GA | F199: NPV257 | G199: Jose Yezith Córdoba Leon | H199: ✔️ | I199: 40793 | J199: 20 | K199: 929 | L199: 37:20:59 | M199: 11:15:22 | N199: 57%
A200: Magnex | B200: Zona Cerrejón | C200: CERREJON 2022 Cabinas-GA | F200: NPY484 | H200: ✔️ | I200: 69990 | J200: 27 | K200: 2997 | L200: 88:29:53 | M200: 21:39:09 | N200: 83%
A201: Magnex | B201: Zona Generación | C201: Frontera Energy Col 2679 | F201: QLT551 | H201: ✔️ | I201: 10484 | J201: 30 | K201: 3376 | L201: 165:25:23 | M201: 54:48:15 | N201: 100%
A202: Magnex | B202: Zona Generación | C202: Frontera Energy Col 2679 | F202: QLT553 | H202: ✔️ | I202: 16570 | J202: 30 | K202: 5937 | L202: 290:46:20 | M202: 56:49:21 | N202: 100%
A203: Magnex | B203: Zona Generación | C203: Frontera Energy Col 2679 | F203: PKU060 | H203: ✔️ | I203: 5225 | J203: 30 | K203: 1591 | L203: 106:01:56 | M203: 19:07:04 | N203: 100%
A204: Magnex | B204: Zona Generación | C204: Frontera Energy Col 2679 | F204: QLT576 | H204: ✔️ | I204: 17762 | J204: 30 | K204: 5750 | L204: 316:15:04 | M204: 98:54:41 | N204: 100%
A205: Magnex | B205: Zona Generación | C205: Frontera Energy Col 2679 | F205: QLT513 | G205: Luis Felipe Gomez Perdomo | H205: ✔️ | I205: 6136 | J205: 30 | K205: 2426 | L205: 117:44:57 | M205: 11:54:32 | N205: 97%
A206: Magnex | B206: Zona Generación | C206: Frontera Energy Col 2679 | F206: QLT538 | H206: ✔️ | I206: 15343 | J206: 30 | K206: 5020 | L206: 259:52:17 | M206: 44:42:25 | N206: 100%
A207: Magnex | B207: Zona Generación | C207: Frontera Energy Col 2679 | F207: PKU280 | H207: ✔️ | I207: 5135 | J207: 8 | K207: 489 | L207: 17:56:12 | M207: 3:07:12 | N207: 17%
A208: Magnex | B208: Zona Generación | C208: Frontera Energy Col 2679 | F208: PKU307 | H208: ✔️ | I208: 9044 | J208: 29 | K208: 3241 | L208: 163:52:34 | M208: 70:20:02 | N208: 97%
A209: Magnex | B209: Zona Generación | C209: Frontera Energy Col 2679 | F209: QLT519 | H209: ✔️ | I209: 12733 | J209: 30 | K209: 4356 | L209: 263:00:00 | M209: 103:52:19 | N209: 100%
A210: Magnex | B210: Zona Generación | C210: Frontera Energy Col 2679 | F210: PKU269 | H210: ✔️ | I210: 15515 | J210: 30 | K210: 5299 | L210: 250:11:16 | M210: 59:24:31 | N210: 100%
A211: Magnex | B211: Zona Generación | C211: Frontera Energy Col 2679 | F211: PKU069 | G211: Luis Enrique Chala | H211: ✔️ | I211: 6657 | J211: 30 | K211: 2084 | L211: 124:58:05 | M211: 21:26:14 | N211: 100%
A212: Magnex | B212: Zona Generación | C212: Frontera Energy Col 2679 | F212: PKU249 | H212: ✔️ | I212: 9328 | J212: 30 | K212: 2702 | L212: 136:49:32 | M212: 54:42:45 | N212: 100%
A213: Magnex | B213: Zona Generación | C213: Frontera Energy Col 2679 | F213: PKU239 | H213: ✔️ | I213: 10558 | J213: 24 | K213: 2348 | L213: 122:35:04 | M213: 56:49:16 | N213: 70%
A214: Magnex | B214: Zona Generación | C214: Frontera Energy Col 2679 | F214: QLT528 | H214: ✔️ | I214: 7450 | J214: 30 | K214: 2744 | L214: 126:19:27 | M214: 91:01:42 | N214: 100%

Sheet Preinstalado
A1: Grupo 1 | B1: Grupo 2 | C1: Grupo 3 | D1: Grupo 4 | E1: Grupo 5 | F1: Vehículo | G1: Conductor actual | H1: GPS | I1: Odómetro KM | J1: Días conducidos | K1: Kilómetros conducidos | L1: Horas conducidas | M1: Tiempo en ralentí | N1: % de utilización (días conducidos)
A2: Magnex | B2: Asset Information | C2: Powertrain and Fuel Type | D2: Internal Combustion Engine | E2: Diesel | F2: QLO286 | H2: ✔️ | I2: 30820 | J2: 30 | K2: 6044 | L2: 324:19:25 | M2: 66:45:57 | N2: 100%
A3: Magnex | B3: Asset Information | C3: Asset Type | D3: Vehicle | F3: QLO286 | H3: ✔️ | I3: 30820 | J3: 30 | K3: 6044 | L3: 324:19:25 | M3: 66:45:57 | N3: 100%
A4: Magnex | B4: Asset Information | C4: Powertrain and Fuel Type | D4: Internal Combustion Engine | E4: Diesel | F4: NPY686 | H4: ✔️ | I4: 24050 | J4: 22 | K4: 1208 | L4: 42:03:04 | M4: 6:15:20 | N4: 73%
A5: Magnex | B5: Asset Information | C5: Asset Type | D5: Vehicle | F5: NPY686 | H5: ✔️ | I5: 24050 | J5: 22 | K5: 1208 | L5: 42:03:04 | M5: 6:15:20 | N5: 73%
A6: Magnex | B6: Asset Information | C6: Powertrain and Fuel Type | D6: Internal Combustion Engine | E6: Diesel | F6: PMV840 | H6: ✔️ | I6: 7510 | J6: 20 | K6: 483 | L6: 37:13:50 | M6: 16:04:40 | N6: 63%
A7: Magnex | B7: Asset Information | C7: Asset Type | D7: Vehicle | F7: PMV840 | H7: ✔️ | I7: 7510 | J7: 20 | K7: 483 | L7: 37:13:50 | M7: 16:04:40 | N7: 63%
A8: Magnex | B8: Asset Information | C8: Powertrain and Fuel Type | D8: Internal Combustion Engine | E8: Diesel | F8: NPY798 | H8: ✔️ | I8: 10809 | J8: 26 | K8: 860 | L8: 66:33:51 | M8: 26:01:28 | N8: 83%
A9: Magnex | B9: Asset Information | C9: Asset Type | D9: Vehicle | F9: NPY798 | H9: ✔️ | I9: 10809 | J9: 26 | K9: 860 | L9: 66:33:51 | M9: 26:01:28 | N9: 83%
A10: Magnex | B10: Asset Information | C10: Powertrain and Fuel Type | D10: Internal Combustion Engine | E10: Diesel | F10: GSO698 | H10: ✔️ | I10: 138492 | J10: 24 | K10: 3187 | L10: 131:38:31 | M10: 39:19:25 | N10: 80%
A11: Magnex | B11: Asset Information | C11: Powertrain and Fuel Type | D11: Manually Classified Powertrain | F11: GSO698 | H11: ✔️ | I11: 138492 | J11: 24 | K11: 3187 | L11: 131:38:31 | M11: 39:19:25 | N11: 80%
A12: Magnex | B12: Asset Information | C12: Asset Type | D12: Vehicle | F12: GSO698 | H12: ✔️ | I12: 138492 | J12: 24 | K12: 3187 | L12: 131:38:31 | M12: 39:19:25 | N12: 80%
A13: Magnex | B13: Asset Information | C13: Powertrain and Fuel Type | D13: Internal Combustion Engine | E13: Diesel | F13: NPY979 | H13: ✔️ | I13: 20833 | J13: 20 | K13: 1701 | L13: 72:58:59 | M13: 28:08:22 | N13: 67%
A14: Magnex | B14: Asset Information | C14: Asset Type | D14: Vehicle | F14: NPY979 | H14: ✔️ | I14: 20833 | J14: 20 | K14: 1701 | L14: 72:58:59 | M14: 28:08:22 | N14: 67%
A15: Magnex | B15: Asset Information | C15: Powertrain and Fuel Type | D15: Internal Combustion Engine | E15: Diesel | F15: NPY794 | H15: ✔️ | I15: 21171 | J15: 22 | K15: 1042 | L15: 57:40:03 | M15: 14:56:14 | N15: 67%
A16: Magnex | B16: Asset Information | C16: Asset Type | D16: Vehicle | F16: NPY794 | H16: ✔️ | I16: 21171 | J16: 22 | K16: 1042 | L16: 57:40:03 | M16: 14:56:14 | N16: 67%
A17: Magnex | B17: Asset Information | C17: Powertrain and Fuel Type | D17: Internal Combustion Engine | E17: Diesel | F17: NPY609 | H17: ✔️ | I17: 18011 | J17: 22 | K17: 1337 | L17: 68:47:36 | M17: 32:43:18 | N17: 67%
A18: Magnex | B18: Asset Information | C18: Asset Type | D18: Vehicle | F18: NPY609 | H18: ✔️ | I18: 18011 | J18: 22 | K18: 1337 | L18: 68:47:36 | M18: 32:43:18 | N18: 67%
A19: Magnex | B19: Asset Information | C19: Powertrain and Fuel Type | D19: Internal Combustion Engine | E19: Diesel | F19: NPY995 | H19: ✔️ | I19: 18436 | J19: 21 | K19: 1167 | L19: 56:30:46 | M19: 23:14:10 | N19: 60%
A20: Magnex | B20: Asset Information | C20: Asset Type | D20: Vehicle | F20: NPY995 | H20: ✔️ | I20: 18436 | J20: 21 | K20: 1167 | L20: 56:30:46 | M20: 23:14:10 | N20: 60%
A21: Magnex | B21: Asset Information | C21: Powertrain and Fuel Type | D21: Internal Combustion Engine | E21: Diesel | F21: JSL414 | H21: ✔️ | I21: 168484 | J21: 9 | K21: 338 | L21: 14:33:52 | M21: 11:17:12 | N21: 20%
A22: Magnex | B22: Asset Information | C22: Asset Type | D22: Vehicle | F22: JSL414 | H22: ✔️ | I22: 168484 | J22: 9 | K22: 338 | L22: 14:33:52 | M22: 11:17:12 | N22: 20%
A23: Magnex | B23: Asset Information | C23: Powertrain and Fuel Type | D23: Internal Combustion Engine | E23: Diesel | F23: GSN681 | H23: ✔️ | I23: 163678 | J23: 20 | K23: 1858 | L23: 75:50:34 | M23: 23:27:37 | N23: 63%
A24: Magnex | B24: Asset Information | C24: Powertrain and Fuel Type | D24: Manually Classified Powertrain | F24: GSN681 | H24: ✔️ | I24: 163678 | J24: 20 | K24: 1858 | L24: 75:50:34 | M24: 23:27:37 | N24: 63%
A25: Magnex | B25: Asset Information | C25: Asset Type | D25: Vehicle | F25: GSN681 | H25: ✔️ | I25: 163678 | J25: 20 | K25: 1858 | L25: 75:50:34 | M25: 23:27:37 | N25: 63%
A26: Magnex | B26: Asset Information | C26: Powertrain and Fuel Type | D26: Internal Combustion Engine | E26: Diesel | F26: NPY976 | H26: ✔️ | I26: 21065 | J26: 19 | K26: 653 | L26: 34:01:42 | M26: 11:30:51 | N26: 47%
A27: Magnex | B27: Asset Information | C27: Asset Type | D27: Vehicle | F27: NPY976 | H27: ✔️ | I27: 21065 | J27: 19 | K27: 653 | L27: 34:01:42 | M27: 11:30:51 | N27: 47%
A28: Magnex | B28: Asset Information | C28: Powertrain and Fuel Type | D28: Internal Combustion Engine | E28: Diesel | F28: NPY986 | H28: ✔️ | I28: 15024 | J28: 18 | K28: 712 | L28: 34:11:37 | M28: 15:33:28 | N28: 50%
A29: Magnex | B29: Asset Information | C29: Asset Type | D29: Vehicle | F29: NPY986 | H29: ✔️ | I29: 15024 | J29: 18 | K29: 712 | L29: 34:11:37 | M29: 15:33:28 | N29: 50%
A30: Magnex | B30: Asset Information | C30: Powertrain and Fuel Type | D30: Internal Combustion Engine | E30: Diesel | F30: NPY990 | H30: ✔️ | I30: 19495 | J30: 21 | K30: 1399 | L30: 62:49:30 | M30: 7:31:40 | N30: 63%
A31: Magnex | B31: Asset Information | C31: Asset Type | D31: Vehicle | F31: NPY990 | H31: ✔️ | I31: 19495 | J31: 21 | K31: 1399 | L31: 62:49:30 | M31: 7:31:40 | N31: 63%
A32: Magnex | B32: Asset Information | C32: Powertrain and Fuel Type | D32: Internal Combustion Engine | E32: Diesel | F32: LJQ948 | H32: ✔️ | I32: 203210 | J32: 16 | K32: 493 | L32: 25:35:39 | M32: 39:08:03 | N32: 47%
A33: Magnex | B33: Asset Information | C33: Asset Type | D33: Vehicle | F33: LJQ948 | H33: ✔️ | I33: 203210 | J33: 16 | K33: 493 | L33: 25:35:39 | M33: 39:08:03 | N33: 47%
A34: Magnex | B34: Asset Information | C34: Powertrain and Fuel Type | D34: Internal Combustion Engine | E34: Diesel | F34: NFX476 | H34: ✔️ | I34: 96440 | J34: 15 | K34: 852 | L34: 38:24:02 | M34: 13:26:16 | N34: 50%
A35: Magnex | B35: Asset Information | C35: Asset Type | D35: Vehicle | F35: NFX476 | H35: ✔️ | I35: 96440 | J35: 15 | K35: 852 | L35: 38:24:02 | M35: 13:26:16 | N35: 50%
A36: Magnex | B36: Asset Information | C36: Powertrain and Fuel Type | D36: Internal Combustion Engine | E36: Diesel | F36: NPY987 | H36: ✔️ | I36: 13527 | J36: 13 | K36: 661 | L36: 31:26:59 | M36: 25:14:00 | N36: 37%
A37: Magnex | B37: Asset Information | C37: Asset Type | D37: Vehicle | F37: NPY987 | H37: ✔️ | I37: 13527 | J37: 13 | K37: 661 | L37: 31:26:59 | M37: 25:14:00 | N37: 37%
A38: Magnex | B38: Asset Information | C38: Powertrain and Fuel Type | D38: Internal Combustion Engine | E38: Diesel | F38: NPY628 | H38: ✔️ | I38: 13083 | J38: 18 | K38: 1046 | L38: 52:27:51 | M38: 63:28:59 | N38: 57%
A39: Magnex | B39: Asset Information | C39: Asset Type | D39: Vehicle | F39: NPY628 | H39: ✔️ | I39: 13083 | J39: 18 | K39: 1046 | L39: 52:27:51 | M39: 63:28:59 | N39: 57%
A40: Magnex | B40: Asset Information | C40: Powertrain and Fuel Type | D40: Internal Combustion Engine | E40: Diesel | F40: NPY978 | H40: ✔️ | I40: 17791 | J40: 17 | K40: 858 | L40: 40:39:02 | M40: 19:50:36 | N40: 47%
A41: Magnex | B41: Asset Information | C41: Asset Type | D41: Vehicle | F41: NPY978 | H41: ✔️ | I41: 17791 | J41: 17 | K41: 858 | L41: 40:39:02 | M41: 19:50:36 | N41: 47%
A42: Magnex | B42: Asset Information | C42: Powertrain and Fuel Type | D42: Internal Combustion Engine | E42: Diesel | F42: JSL356 | H42: ✔️ | I42: 178134 | J42: 12 | K42: 565 | L42: 41:03:45 | M42: 42:38:31 | N42: 33%
A43: Magnex | B43: Asset Information | C43: Asset Type | D43: Vehicle | F43: JSL356 | H43: ✔️ | I43: 178134 | J43: 12 | K43: 565 | L43: 41:03:45 | M43: 42:38:31 | N43: 33%
A44: Magnex | B44: Asset Information | C44: Powertrain and Fuel Type | D44: Internal Combustion Engine | E44: Diesel | F44: NPZ118 | H44: ✔️ | I44: 21418 | J44: 13 | K44: 373 | L44: 17:48:43 | M44: 8:24:11 | N44: 30%
A45: Magnex | B45: Asset Information | C45: Asset Type | D45: Vehicle | F45: NPZ118 | H45: ✔️ | I45: 21418 | J45: 13 | K45: 373 | L45: 17:48:43 | M45: 8:24:11 | N45: 30%
A46: Magnex | B46: Asset Information | C46: Powertrain and Fuel Type | D46: Internal Combustion Engine | E46: Diesel | F46: GEU353 | H46: ✔️ | I46: 117720 | J46: 14 | K46: 512 | L46: 25:11:37 | M46: 10:29:48 | N46: 40%
A47: Magnex | B47: Asset Information | C47: Asset Type | D47: Vehicle | F47: GEU353 | H47: ✔️ | I47: 117720 | J47: 14 | K47: 512 | L47: 25:11:37 | M47: 10:29:48 | N47: 40%
A48: Magnex | B48: Asset Information | C48: Powertrain and Fuel Type | D48: Internal Combustion Engine | E48: Diesel | F48: NPY988 | H48: ✔️ | I48: 17532 | J48: 14 | K48: 623 | L48: 30:06:28 | M48: 5:22:00 | N48: 33%
A49: Magnex | B49: Asset Information | C49: Asset Type | D49: Vehicle | F49: NPY988 | H49: ✔️ | I49: 17532 | J49: 14 | K49: 623 | L49: 30:06:28 | M49: 5:22:00 | N49: 33%
A50: Magnex | B50: Asset Information | C50: Powertrain and Fuel Type | D50: Internal Combustion Engine | E50: Diesel | F50: PMV835 | H50: ✔️ | I50: 13136 | J50: 14 | K50: 431 | L50: 20:31:47 | M50: 6:12:18 | N50: 33%
A51: Magnex | B51: Asset Information | C51: Asset Type | D51: Vehicle | F51: PMV835 | H51: ✔️ | I51: 13136 | J51: 14 | K51: 431 | L51: 20:31:47 | M51: 6:12:18 | N51: 33%
A52: Magnex | B52: Asset Information | C52: Powertrain and Fuel Type | D52: Internal Combustion Engine | E52: Diesel | F52: NPY973 | H52: ✔️ | I52: 16314 | J52: 10 | K52: 426 | L52: 26:31:06 | M52: 10:06:23 | N52: 30%
A53: Magnex | B53: Asset Information | C53: Asset Type | D53: Vehicle | F53: NPY973 | H53: ✔️ | I53: 16314 | J53: 10 | K53: 426 | L53: 26:31:06 | M53: 10:06:23 | N53: 30%
A54: Magnex | B54: Asset Information | C54: Powertrain and Fuel Type | D54: Internal Combustion Engine | E54: Diesel | F54: NPY797 | H54: ✔️ | I54: 24510 | J54: 11 | K54: 727 | L54: 35:58:06 | M54: 18:46:22 | N54: 33%
A55: Magnex | B55: Asset Information | C55: Asset Type | D55: Vehicle | F55: NPY797 | H55: ✔️ | I55: 24510 | J55: 11 | K55: 727 | L55: 35:58:06 | M55: 18:46:22 | N55: 33%
A56: Magnex | B56: Asset Information | C56: Powertrain and Fuel Type | D56: Internal Combustion Engine | E56: Diesel | F56: WNN254 | H56: ✔️ | I56: 76569 | J56: 13 | K56: 529 | L56: 32:26:16 | M56: 50:35:40 | N56: 40%
A57: Magnex | B57: Asset Information | C57: Asset Type | D57: Vehicle | F57: WNN254 | H57: ✔️ | I57: 76569 | J57: 13 | K57: 529 | L57: 32:26:16 | M57: 50:35:40 | N57: 40%
A58: Magnex | B58: Asset Information | C58: Powertrain and Fuel Type | D58: Internal Combustion Engine | E58: Diesel | F58: PMV839 | H58: ✔️ | I58: 14400 | J58: 10 | K58: 460 | L58: 20:38:48 | M58: 1:56:43 | N58: 30%
A59: Magnex | B59: Asset Information | C59: Asset Type | D59: Vehicle | F59: PMV839 | H59: ✔️ | I59: 14400 | J59: 10 | K59: 460 | L59: 20:38:48 | M59: 1:56:43 | N59: 30%
A60: Magnex | B60: Asset Information | C60: Powertrain and Fuel Type | D60: Internal Combustion Engine | E60: Diesel | F60: NPY966 | H60: ✔️ | I60: 22609 | J60: 8 | K60: 116 | L60: 9:02:31 | M60: 3:52:33 | N60: 23%
A61: Magnex | B61: Asset Information | C61: Asset Type | D61: Vehicle | F61: NPY966 | H61: ✔️ | I61: 22609 | J61: 8 | K61: 116 | L61: 9:02:31 | M61: 3:52:33 | N61: 23%
A62: Magnex | B62: Asset Information | C62: Powertrain and Fuel Type | D62: Internal Combustion Engine | E62: Diesel | F62: PMV833 | H62: ✔️ | I62: 13745 | J62: 10 | K62: 467 | L62: 23:36:14 | M62: 9:08:05 | N62: 30%
A63: Magnex | B63: Asset Information | C63: Asset Type | D63: Vehicle | F63: PMV833 | H63: ✔️ | I63: 13745 | J63: 10 | K63: 467 | L63: 23:36:14 | M63: 9:08:05 | N63: 30%
A64: Magnex | B64: Asset Information | C64: Powertrain and Fuel Type | D64: Internal Combustion Engine | E64: Diesel | F64: LMM822 | H64: ✔️ | I64: 348313 | J64: 15 | K64: 332 | L64: 21:01:45 | M64: 25:02:00 | N64: 40%
A65: Magnex | B65: Asset Information | C65: Asset Type | D65: Vehicle | F65: LMM822 | H65: ✔️ | I65: 348313 | J65: 15 | K65: 332 | L65: 21:01:45 | M65: 25:02:00 | N65: 40%
A66: Magnex | B66: Asset Information | C66: Powertrain and Fuel Type | D66: Internal Combustion Engine | E66: Diesel | F66: PMW018 | H66: ✔️ | I66: 14296 | J66: 11 | K66: 433 | L66: 18:56:28 | M66: 6:09:44 | N66: 33%
A67: Magnex | B67: Asset Information | C67: Asset Type | D67: Vehicle | F67: PMW018 | H67: ✔️ | I67: 14296 | J67: 11 | K67: 433 | L67: 18:56:28 | M67: 6:09:44 | N67: 33%
A68: Magnex | B68: Asset Information | C68: Powertrain and Fuel Type | D68: Internal Combustion Engine | E68: Diesel | F68: NPY991 | H68: ✔️ | I68: 25281 | J68: 12 | K68: 1334 | L68: 50:56:11 | M68: 9:37:02 | N68: 40%
A69: Magnex | B69: Asset Information | C69: Asset Type | D69: Vehicle | F69: NPY991 | H69: ✔️ | I69: 25281 | J69: 12 | K69: 1334 | L69: 50:56:11 | M69: 9:37:02 | N69: 40%
A70: Magnex | B70: Asset Information | C70: Powertrain and Fuel Type | D70: Internal Combustion Engine | E70: Diesel | F70: LWL497 | H70: ✔️ | I70: 183477 | J70: 10 | K70: 330 | L70: 17:19:23 | M70: 18:05:53 | N70: 20%
A71: Magnex | B71: Asset Information | C71: Asset Type | D71: Vehicle | F71: LWL497 | H71: ✔️ | I71: 183477 | J71: 10 | K71: 330 | L71: 17:19:23 | M71: 18:05:53 | N71: 20%
A72: Magnex | B72: Asset Information | C72: Powertrain and Fuel Type | D72: Internal Combustion Engine | E72: Diesel | F72: NPY799 | H72: ✔️ | I72: 15456 | J72: 14 | K72: 378 | L72: 17:45:03 | M72: 3:08:49 | N72: 27%
A73: Magnex | B73: Asset Information | C73: Asset Type | D73: Vehicle | F73: NPY799 | H73: ✔️ | I73: 15456 | J73: 14 | K73: 378 | L73: 17:45:03 | M73: 3:08:49 | N73: 27%
A74: Magnex | B74: Asset Information | C74: Powertrain and Fuel Type | D74: Internal Combustion Engine | E74: Diesel | F74: NPY796 | H74: ✔️ | I74: 12945 | J74: 13 | K74: 353 | L74: 24:12:31 | M74: 19:48:39 | N74: 33%
A75: Magnex | B75: Asset Information | C75: Asset Type | D75: Vehicle | F75: NPY796 | H75: ✔️ | I75: 12945 | J75: 13 | K75: 353 | L75: 24:12:31 | M75: 19:48:39 | N75: 33%
A76: Magnex | B76: Asset Information | C76: Powertrain and Fuel Type | D76: Internal Combustion Engine | E76: Diesel | F76: NPY981 | H76: ✔️ | I76: 14982 | J76: 6 | K76: 2 | L76: 0:55:24 | M76: 2:12:05 | N76: 3%
A77: Magnex | B77: Asset Information | C77: Asset Type | D77: Vehicle | F77: NPY981 | H77: ✔️ | I77: 14982 | J77: 6 | K77: 2 | L77: 0:55:24 | M77: 2:12:05 | N77: 3%
A78: Magnex | B78: Asset Information | C78: Powertrain and Fuel Type | D78: Internal Combustion Engine | E78: Diesel | F78: NPY786 | H78: ✔️ | I78: 15508 | J78: 11 | K78: 411 | L78: 33:00:25 | M78: 20:46:13 | N78: 37%
A79: Magnex | B79: Asset Information | C79: Asset Type | D79: Vehicle | F79: NPY786 | H79: ✔️ | I79: 15508 | J79: 11 | K79: 411 | L79: 33:00:25 | M79: 20:46:13 | N79: 37%
A80: Magnex | B80: Asset Information | C80: Powertrain and Fuel Type | D80: Internal Combustion Engine | E80: Diesel | F80: NPY972 | H80: ✔️ | I80: 27075 | J80: 14 | K80: 753 | L80: 43:33:59 | M80: 11:09:15 | N80: 47%
A81: Magnex | B81: Asset Information | C81: Asset Type | D81: Vehicle | F81: NPY972 | H81: ✔️ | I81: 27075 | J81: 14 | K81: 753 | L81: 43:33:59 | M81: 11:09:15 | N81: 47%
A82: Magnex | B82: Asset Information | C82: Powertrain and Fuel Type | D82: Internal Combustion Engine | E82: Diesel | F82: NPY791 | H82: ✔️ | I82: 10463 | J82: 11 | K82: 339 | L82: 28:52:17 | M82: 17:29:02 | N82: 37%
A83: Magnex | B83: Asset Information | C83: Asset Type | D83: Vehicle | F83: NPY791 | H83: ✔️ | I83: 10463 | J83: 11 | K83: 339 | L83: 28:52:17 | M83: 17:29:02 | N83: 37%
A84: Magnex | B84: Asset Information | C84: Powertrain and Fuel Type | D84: Internal Combustion Engine | E84: Diesel | F84: NPY789 | H84: ✔️ | I84: 12156 | J84: 14 | K84: 493 | L84: 31:10:13 | M84: 23:08:16 | N84: 43%
A85: Magnex | B85: Asset Information | C85: Asset Type | D85: Vehicle | F85: NPY789 | H85: ✔️ | I85: 12156 | J85: 14 | K85: 493 | L85: 31:10:13 | M85: 23:08:16 | N85: 43%
A86: Magnex | B86: Asset Information | C86: Powertrain and Fuel Type | D86: Internal Combustion Engine | E86: Diesel | F86: NPY793 | H86: ✔️ | I86: 9200 | J86: 14 | K86: 259 | L86: 19:17:11 | M86: 4:54:47 | N86: 27%
A87: Magnex | B87: Asset Information | C87: Asset Type | D87: Vehicle | F87: NPY793 | H87: ✔️ | I87: 9200 | J87: 14 | K87: 259 | L87: 19:17:11 | M87: 4:54:47 | N87: 27%
A88: Magnex | B88: Asset Information | C88: Powertrain and Fuel Type | D88: Internal Combustion Engine | E88: Diesel | F88: NPY790 | H88: ✔️ | I88: 9581 | J88: 6 | K88: 60 | L88: 5:48:05 | M88: 5:07:35 | N88: 10%
A89: Magnex | B89: Asset Information | C89: Asset Type | D89: Vehicle | F89: NPY790 | H89: ✔️ | I89: 9581 | J89: 6 | K89: 60 | L89: 5:48:05 | M89: 5:07:35 | N89: 10%
A90: Magnex | B90: Asset Information | C90: Powertrain and Fuel Type | D90: Internal Combustion Engine | E90: Diesel | F90: NPY950 | H90: ✔️ | I90: 10700 | J90: 14 | K90: 506 | L90: 33:32:09 | M90: 24:34:59 | N90: 43%
A91: Magnex | B91: Asset Information | C91: Asset Type | D91: Vehicle | F91: NPY950 | H91: ✔️ | I91: 10700 | J91: 14 | K91: 506 | L91: 33:32:09 | M91: 24:34:59 | N91: 43%
A92: Magnex | B92: Asset Information | C92: Powertrain and Fuel Type | D92: Internal Combustion Engine | E92: Gasoline or Petrol | F92: NZT860 | H92: ✔️ | I92: 12092 | J92: 11 | K92: 661 | L92: 38:18:06 | M92: 14:38:42 | N92: 33%
A93: Magnex | B93: Asset Information | C93: Asset Type | D93: Vehicle | F93: NZT860 | H93: ✔️ | I93: 12092 | J93: 11 | K93: 661 | L93: 38:18:06 | M93: 14:38:42 | N93: 33%
A94: Magnex | B94: Asset Information | C94: Powertrain and Fuel Type | D94: Internal Combustion Engine | E94: Diesel | F94: NPY787 | H94: ✔️ | I94: 29442 | J94: 5 | K94: 421 | L94: 11:31:36 | M94: 0:59:43 | N94: 17%
A95: Magnex | B95: Asset Information | C95: Asset Type | D95: Vehicle | F95: NPY787 | H95: ✔️ | I95: 29442 | J95: 5 | K95: 421 | L95: 11:31:36 | M95: 0:59:43 | N95: 17%
A96: Magnex | B96: Asset Information | C96: Powertrain and Fuel Type | D96: Internal Combustion Engine | E96: Diesel | F96: LHW539 | H96: ✔️ | I96: 116141 | J96: 8 | K96: 745 | L96: 18:33:06 | M96: 1:34:18 | N96: 23%
A97: Magnex | B97: Asset Information | C97: Powertrain and Fuel Type | D97: Manually Classified Powertrain | F97: LHW539 | H97: ✔️ | I97: 116141 | J97: 8 | K97: 745 | L97: 18:33:06 | M97: 1:34:18 | N97: 23%
A98: Magnex | B98: Asset Information | C98: Asset Type | D98: Vehicle | F98: LHW539 | H98: ✔️ | I98: 116141 | J98: 8 | K98: 745 | L98: 18:33:06 | M98: 1:34:18 | N98: 23%
A99: Magnex | B99: Asset Information | C99: Powertrain and Fuel Type | D99: Internal Combustion Engine | E99: Diesel | F99: NPY969 | H99: ✔️ | I99: 11371 | J99: 10 | K99: 387 | L99: 20:35:24 | M99: 11:33:15 | N99: 33%
A100: Magnex | B100: Asset Information | C100: Asset Type | D100: Vehicle | F100: NPY969 | H100: ✔️ | I100: 11371 | J100: 10 | K100: 387 | L100: 20:35:24 | M100: 11:33:15 | N100: 33%
...
